Workbook

Sheet Key Ratio
A1: KEY RATIO - PT Rukun Raharja Tbk (RAJA)
A4: Keterangan | B4: 12M 2016 | C4: 12M 2017 | D4: 12M 2018 | E4: 12M 2019 | F4: 12M 2020 | G4: 12M 2021 | H4: 12M 2022 | I4: 12M 2023 | J4: 12M 2024 | K4: 12M 2025 | M4: Catatan
A5: VALUASI & PROFITABILITAS
A6: Share Outstanding (Miliar Lembar) | B6: =INDEX('Income Statement'!$B$42:$K$42,MATCH(B$4,'Income Statement'!$B$4:$K$4,0)) -> 4.08 | C6: =INDEX('Income Statement'!$B$42:$K$42,MATCH(C$4,'Income Statement'!$B$4:$K$4,0)) -> 4.08 | D6: =INDEX('Income Statement'!$B$42:$K$42,MATCH(D$4,'Income Statement'!$B$4:$K$4,0)) -> 4.23 | E6: =INDEX('Income Statement'!$B$42:$K$42,MATCH(E$4,'Income Statement'!$B$4:$K$4,0)) -> 4.23 | F6: =INDEX('Income Statement'!$B$42:$K$42,MATCH(F$4,'Income Statement'!$B$4:$K$4,0)) -> 4.23 | G6: =INDEX('Income Statement'!$B$42:$K$42,MATCH(G$4,'Income Statement'!$B$4:$K$4,0)) -> 4.23 | H6: =INDEX('Income Statement'!$B$42:$K$42,MATCH(H$4,'Income Statement'!$B$4:$K$4,0)) -> 4.23 | I6: =INDEX('Income Statement'!$B$42:$K$42,MATCH(I$4,'Income Statement'!$B$4:$K$4,0)) -> 4.23 | ... K6: =INDEX('Income Statement'!$B$42:$K$42,MATCH(K$4,'Income Statement'!$B$4:$K$4,0)) -> 4.23
A7: EPS (Annual) (Rp) | B7: =INDEX('Income Statement'!$B$30:$K$30,MATCH(B$4,'Income Statement'!$B$4:$K$4,0))/B6 -> 21.323529 | C7: =INDEX('Income Statement'!$B$30:$K$30,MATCH(C$4,'Income Statement'!$B$4:$K$4,0))/C6 -> 38.235294 | D7: =INDEX('Income Statement'!$B$30:$K$30,MATCH(D$4,'Income Statement'!$B$4:$K$4,0))/D6 -> 38.534279 | E7: =INDEX('Income Statement'!$B$30:$K$30,MATCH(E$4,'Income Statement'!$B$4:$K$4,0))/E6 -> 19.148936 | F7: =INDEX('Income Statement'!$B$30:$K$30,MATCH(F$4,'Income Statement'!$B$4:$K$4,0))/F6 -> 4.7281324 | G7: =INDEX('Income Statement'!$B$30:$K$30,MATCH(G$4,'Income Statement'!$B$4:$K$4,0))/G6 -> 7.5650118 | H7: =INDEX('Income Statement'!$B$30:$K$30,MATCH(H$4,'Income Statement'!$B$4:$K$4,0))/H6 -> 30.969267 | I7: =INDEX('Income Statement'!$B$30:$K$30,MATCH(I$4,'Income Statement'!$B$4:$K$4,0))/I6 -> 92.434988 | ... K7: =INDEX('Income Statement'!$B$30:$K$30,MATCH(K$4,'Income Statement'!$B$4:$K$4,0))/K6 -> 106.14657
A8: PE Ratio (Annual) | B8: =INDEX('Market Data'!$B$31:$K$31,MATCH(B$4,'Market Data'!$B$24:$K$24,0)) -> 9.3793103 | C8: =INDEX('Market Data'!$B$31:$K$31,MATCH(C$4,'Market Data'!$B$24:$K$24,0)) -> 7.8461538 | D8: =INDEX('Market Data'!$B$31:$K$31,MATCH(D$4,'Market Data'!$B$24:$K$24,0)) -> 8.4340491 | E8: =INDEX('Market Data'!$B$31:$K$31,MATCH(E$4,'Market Data'!$B$24:$K$24,0)) -> 9.9222222 | F8: =INDEX('Market Data'!$B$31:$K$31,MATCH(F$4,'Market Data'!$B$24:$K$24,0)) -> 52.875 | G8: =INDEX('Market Data'!$B$31:$K$31,MATCH(G$4,'Market Data'!$B$24:$K$24,0)) -> 23.79375 | H8: =INDEX('Market Data'!$B$31:$K$31,MATCH(H$4,'Market Data'!$B$24:$K$24,0)) -> 33.90458 | I8: =INDEX('Market Data'!$B$31:$K$31,MATCH(I$4,'Market Data'!$B$24:$K$24,0)) -> 15.253964 | ... K8: =INDEX('Market Data'!$B$31:$K$31,MATCH(K$4,'Market Data'!$B$24:$K$24,0)) -> 57.467706
A9: Price to Sales (Annual) | B9: =INDEX('Market Data'!$B$32:$K$32,MATCH(B$4,'Market Data'!$B$24:$K$24,0)) -> 0.32810615 | C9: =INDEX('Market Data'!$B$32:$K$32,MATCH(C$4,'Market Data'!$B$24:$K$24,0)) -> 0.61414952 | D9: =INDEX('Market Data'!$B$32:$K$32,MATCH(D$4,'Market Data'!$B$24:$K$24,0)) -> 0.81684492 | E9: =INDEX('Market Data'!$B$32:$K$32,MATCH(E$4,'Market Data'!$B$24:$K$24,0)) -> 0.46510417 | F9: =INDEX('Market Data'!$B$32:$K$32,MATCH(F$4,'Market Data'!$B$24:$K$24,0)) -> 0.734375 | G9: =INDEX('Market Data'!$B$32:$K$32,MATCH(G$4,'Market Data'!$B$24:$K$24,0)) -> 0.54192171 | H9: =INDEX('Market Data'!$B$32:$K$32,MATCH(H$4,'Market Data'!$B$24:$K$24,0)) -> 2.3562334 | I9: =INDEX('Market Data'!$B$32:$K$32,MATCH(I$4,'Market Data'!$B$24:$K$24,0)) -> 1.9190154 | ... K9: =INDEX('Market Data'!$B$32:$K$32,MATCH(K$4,'Market Data'!$B$24:$K$24,0)) -> 5.8723259
A10: EBITDA (Annual) | B10: n/a | C10: n/a | D10: 184.57 | E10: 136.69 | F10: 187.66 | G10: 175.74 | H10: 334.92 | I10: 1000.02 | J10: 1105.93 | K10: 1126.33
A11: Return on Assets - ROA (Annual) | B11: =INDEX('Income Statement'!$B$30:$K$30,MATCH(B$4,'Income Statement'!$B$4:$K$4,0))/INDEX('Balance Sheet'!$B$26:$K$26,MATCH(B$4,'Balance Sheet'!$B$4:$K$4,0)) -> 0.044592517 | C11: =INDEX('Income Statement'!$B$30:$K$30,MATCH(C$4,'Income Statement'!$B$4:$K$4,0))/INDEX('Balance Sheet'!$B$26:$K$26,MATCH(C$4,'Balance Sheet'!$B$4:$K$4,0)) -> 0.076508092 | D11: =INDEX('Income Statement'!$B$30:$K$30,MATCH(D$4,'Income Statement'!$B$4:$K$4,0))/INDEX('Balance Sheet'!$B$26:$K$26,MATCH(D$4,'Balance Sheet'!$B$4:$K$4,0)) -> 0.058908565 | E11: =INDEX('Income Statement'!$B$30:$K$30,MATCH(E$4,'Income Statement'!$B$4:$K$4,0))/INDEX('Balance Sheet'!$B$26:$K$26,MATCH(E$4,'Balance Sheet'!$B$4:$K$4,0)) -> 0.032296651 | F11: =INDEX('Income Statement'!$B$30:$K$30,MATCH(F$4,'Income Statement'!$B$4:$K$4,0))/INDEX('Balance Sheet'!$B$26:$K$26,MATCH(F$4,'Balance Sheet'!$B$4:$K$4,0)) -> 0.0085070183 | G11: =INDEX('Income Statement'!$B$30:$K$30,MATCH(G$4,'Income Statement'!$B$4:$K$4,0))/INDEX('Balance Sheet'!$B$26:$K$26,MATCH(G$4,'Balance Sheet'!$B$4:$K$4,0)) -> 0.0091272105 | H11: =INDEX('Income Statement'!$B$30:$K$30,MATCH(H$4,'Income Statement'!$B$4:$K$4,0))/INDEX('Balance Sheet'!$B$26:$K$26,MATCH(H$4,'Balance Sheet'!$B$4:$K$4,0)) -> 0.032250123 | I11: =INDEX('Income Statement'!$B$30:$K$30,MATCH(I$4,'Income Statement'!$B$4:$K$4,0))/INDEX('Balance Sheet'!$B$26:$K$26,MATCH(I$4,'Balance Sheet'!$B$4:$K$4,0)) -> 0.077059519 | ... K11: =INDEX('Income Statement'!$B$30:$K$30,MATCH(K$4,'Income Statement'!$B$4:$K$4,0))/INDEX('Balance Sheet'!$B$26:$K$26,MATCH(K$4,'Balance Sheet'!$B$4:$K$4,0)) -> 0.056223391
A12: Return on Equity - ROE (Annual) | B12: =INDEX('Income Statement'!$B$30:$K$30,MATCH(B$4,'Income Statement'!$B$4:$K$4,0))/(INDEX('Balance Sheet'!$B$77:$K$77,MATCH(B$4,'Balance Sheet'!$B$4:$K$4,0))-INDEX('Balance Sheet'!$B$75:$K$75,MATCH(B$4,'Balance Sheet'!$B$4:$K$4,0))) -> 0.093952484 | C12: =INDEX('Income Statement'!$B$30:$K$30,MATCH(C$4,'Income Statement'!$B$4:$K$4,0))/(INDEX('Balance Sheet'!$B$77:$K$77,MATCH(C$4,'Balance Sheet'!$B$4:$K$4,0))-INDEX('Balance Sheet'!$B$75:$K$75,MATCH(C$4,'Balance Sheet'!$B$4:$K$4,0))) -> 0.14511628 | D12: =INDEX('Income Statement'!$B$30:$K$30,MATCH(D$4,'Income Statement'!$B$4:$K$4,0))/(INDEX('Balance Sheet'!$B$77:$K$77,MATCH(D$4,'Balance Sheet'!$B$4:$K$4,0))-INDEX('Balance Sheet'!$B$75:$K$75,MATCH(D$4,'Balance Sheet'!$B$4:$K$4,0))) -> 0.12264861 | E12: =INDEX('Income Statement'!$B$30:$K$30,MATCH(E$4,'Income Statement'!$B$4:$K$4,0))/(INDEX('Balance Sheet'!$B$77:$K$77,MATCH(E$4,'Balance Sheet'!$B$4:$K$4,0))-INDEX('Balance Sheet'!$B$75:$K$75,MATCH(E$4,'Balance Sheet'!$B$4:$K$4,0))) -> 0.057569296 | F12: =INDEX('Income Statement'!$B$30:$K$30,MATCH(F$4,'Income Statement'!$B$4:$K$4,0))/(INDEX('Balance Sheet'!$B$77:$K$77,MATCH(F$4,'Balance Sheet'!$B$4:$K$4,0))-INDEX('Balance Sheet'!$B$75:$K$75,MATCH(F$4,'Balance Sheet'!$B$4:$K$4,0))) -> 0.014054814 | G12: =INDEX('Income Statement'!$B$30:$K$30,MATCH(G$4,'Income Statement'!$B$4:$K$4,0))/(INDEX('Balance Sheet'!$B$77:$K$77,MATCH(G$4,'Balance Sheet'!$B$4:$K$4,0))-INDEX('Balance Sheet'!$B$75:$K$75,MATCH(G$4,'Balance Sheet'!$B$4:$K$4,0))) -> 0.0220234 | H12: =INDEX('Income Statement'!$B$30:$K$30,MATCH(H$4,'Income Statement'!$B$4:$K$4,0))/(INDEX('Balance Sheet'!$B$77:$K$77,MATCH(H$4,'Balance Sheet'!$B$4:$K$4,0))-INDEX('Balance Sheet'!$B$75:$K$75,MATCH(H$4,'Balance Sheet'!$B$4:$K$4,0))) -> 0.077331759 | I12: =INDEX('Income Statement'!$B$30:$K$30,MATCH(I$4,'Income Statement'!$B$4:$K$4,0))/(INDEX('Balance Sheet'!$B$77:$K$77,MATCH(I$4,'Balance Sheet'!$B$4:$K$4,0))-INDEX('Balance Sheet'!$B$75:$K$75,MATCH(I$4,'Balance Sheet'!$B$4:$K$4,0))) -> 0.1954023 | ... K12: =INDEX('Income Statement'!$B$30:$K$30,MATCH(K$4,'Income Statement'!$B$4:$K$4,0))/(INDEX('Balance Sheet'!$B$77:$K$77,MATCH(K$4,'Balance Sheet'!$B$4:$K$4,0))-INDEX('Balance Sheet'!$B$75:$K$75,MATCH(K$4,'Balance Sheet'!$B$4:$K$4,0))) -> 0.1260174
A13: Return on Capital Employed - ROCE (Annual) | B13: =INDEX('Income Statement'!$B$9:$K$9,MATCH(B$4,'Income Statement'!$B$4:$K$4,0))/(INDEX('Balance Sheet'!$B$26:$K$26,MATCH(B$4,'Balance Sheet'!$B$4:$K$4,0))-INDEX('Balance Sheet'!$B$50:$K$50,MATCH(B$4,'Balance Sheet'!$B$4:$K$4,0))) -> 0.093446602 | C13: =INDEX('Income Statement'!$B$9:$K$9,MATCH(C$4,'Income Statement'!$B$4:$K$4,0))/(INDEX('Balance Sheet'!$B$26:$K$26,MATCH(C$4,'Balance Sheet'!$B$4:$K$4,0))-INDEX('Balance Sheet'!$B$50:$K$50,MATCH(C$4,'Balance Sheet'!$B$4:$K$4,0))) -> 0.014899713 | D13: =INDEX('Income Statement'!$B$9:$K$9,MATCH(D$4,'Income Statement'!$B$4:$K$4,0))/(INDEX('Balance Sheet'!$B$26:$K$26,MATCH(D$4,'Balance Sheet'!$B$4:$K$4,0))-INDEX('Balance Sheet'!$B$50:$K$50,MATCH(D$4,'Balance Sheet'!$B$4:$K$4,0))) -> 0.035073735 | E13: =INDEX('Income Statement'!$B$9:$K$9,MATCH(E$4,'Income Statement'!$B$4:$K$4,0))/(INDEX('Balance Sheet'!$B$26:$K$26,MATCH(E$4,'Balance Sheet'!$B$4:$K$4,0))-INDEX('Balance Sheet'!$B$50:$K$50,MATCH(E$4,'Balance Sheet'!$B$4:$K$4,0))) -> 0.018340211 | F13: =INDEX('Income Statement'!$B$9:$K$9,MATCH(F$4,'Income Statement'!$B$4:$K$4,0))/(INDEX('Balance Sheet'!$B$26:$K$26,MATCH(F$4,'Balance Sheet'!$B$4:$K$4,0))-INDEX('Balance Sheet'!$B$50:$K$50,MATCH(F$4,'Balance Sheet'!$B$4:$K$4,0))) -> 0.04062653 | G13: =INDEX('Income Statement'!$B$9:$K$9,MATCH(G$4,'Income Statement'!$B$4:$K$4,0))/(INDEX('Balance Sheet'!$B$26:$K$26,MATCH(G$4,'Balance Sheet'!$B$4:$K$4,0))-INDEX('Balance Sheet'!$B$50:$K$50,MATCH(G$4,'Balance Sheet'!$B$4:$K$4,0))) -> 0.020465116 | H13: =INDEX('Income Statement'!$B$9:$K$9,MATCH(H$4,'Income Statement'!$B$4:$K$4,0))/(INDEX('Balance Sheet'!$B$26:$K$26,MATCH(H$4,'Balance Sheet'!$B$4:$K$4,0))-INDEX('Balance Sheet'!$B$50:$K$50,MATCH(H$4,'Balance Sheet'!$B$4:$K$4,0))) -> 0.050535567 | I13: =INDEX('Income Statement'!$B$9:$K$9,MATCH(I$4,'Income Statement'!$B$4:$K$4,0))/(INDEX('Balance Sheet'!$B$26:$K$26,MATCH(I$4,'Balance Sheet'!$B$4:$K$4,0))-INDEX('Balance Sheet'!$B$50:$K$50,MATCH(I$4,'Balance Sheet'!$B$4:$K$4,0))) -> 0.17435775 | ... K13: =INDEX('Income Statement'!$B$9:$K$9,MATCH(K$4,'Income Statement'!$B$4:$K$4,0))/(INDEX('Balance Sheet'!$B$26:$K$26,MATCH(K$4,'Balance Sheet'!$B$4:$K$4,0))-INDEX('Balance Sheet'!$B$50:$K$50,MATCH(K$4,'Balance Sheet'!$B$4:$K$4,0))) -> 0.12077597
A14: Interest Coverage (Annual) | B14: =INDEX('Income Statement'!$B$9:$K$9,MATCH(B$4,'Income Statement'!$B$4:$K$4,0))/ABS(INDEX('Income Statement'!$B$14:$K$14,MATCH(B$4,'Income Statement'!$B$4:$K$4,0))) -> 2.9615385 | C14: =INDEX('Income Statement'!$B$9:$K$9,MATCH(C$4,'Income Statement'!$B$4:$K$4,0))/ABS(INDEX('Income Statement'!$B$14:$K$14,MATCH(C$4,'Income Statement'!$B$4:$K$4,0))) -> 0.35135135 | D14: =INDEX('Income Statement'!$B$9:$K$9,MATCH(D$4,'Income Statement'!$B$4:$K$4,0))/ABS(INDEX('Income Statement'!$B$14:$K$14,MATCH(D$4,'Income Statement'!$B$4:$K$4,0))) -> 0.93617021 | E14: =INDEX('Income Statement'!$B$9:$K$9,MATCH(E$4,'Income Statement'!$B$4:$K$4,0))/ABS(INDEX('Income Statement'!$B$14:$K$14,MATCH(E$4,'Income Statement'!$B$4:$K$4,0))) -> 0.85106383 | F14: =INDEX('Income Statement'!$B$9:$K$9,MATCH(F$4,'Income Statement'!$B$4:$K$4,0))/ABS(INDEX('Income Statement'!$B$14:$K$14,MATCH(F$4,'Income Statement'!$B$4:$K$4,0))) -> 1.8863636 | G14: =INDEX('Income Statement'!$B$9:$K$9,MATCH(G$4,'Income Statement'!$B$4:$K$4,0))/ABS(INDEX('Income Statement'!$B$14:$K$14,MATCH(G$4,'Income Statement'!$B$4:$K$4,0))) -> 1.8857143 | H14: =INDEX('Income Statement'!$B$9:$K$9,MATCH(H$4,'Income Statement'!$B$4:$K$4,0))/ABS(INDEX('Income Statement'!$B$14:$K$14,MATCH(H$4,'Income Statement'!$B$4:$K$4,0))) -> 4.6 | I14: =INDEX('Income Statement'!$B$9:$K$9,MATCH(I$4,'Income Statement'!$B$4:$K$4,0))/ABS(INDEX('Income Statement'!$B$14:$K$14,MATCH(I$4,'Income Statement'!$B$4:$K$4,0))) -> 5.1985816 | ... K14: =INDEX('Income Statement'!$B$9:$K$9,MATCH(K$4,'Income Statement'!$B$4:$K$4,0))/ABS(INDEX('Income Statement'!$B$14:$K$14,MATCH(K$4,'Income Statement'!$B$4:$K$4,0))) -> 4.6506024
A16: VALUASI BUKU (BOOK VALUE)
A17: Price to Book Value (Annual) | B17: =INDEX('Market Data'!$B$33:$K$33,MATCH(B$4,'Market Data'!$B$24:$K$24,0)) -> 0.8812095 | C17: =INDEX('Market Data'!$B$33:$K$33,MATCH(C$4,'Market Data'!$B$24:$K$24,0)) -> 1.1386047 | D17: =INDEX('Market Data'!$B$33:$K$33,MATCH(D$4,'Market Data'!$B$24:$K$24,0)) -> 1.0344244 | E17: =INDEX('Market Data'!$B$33:$K$33,MATCH(E$4,'Market Data'!$B$24:$K$24,0)) -> 0.57121535 | F17: =INDEX('Market Data'!$B$33:$K$33,MATCH(F$4,'Market Data'!$B$24:$K$24,0)) -> 0.74314828 | G17: =INDEX('Market Data'!$B$33:$K$33,MATCH(G$4,'Market Data'!$B$24:$K$24,0)) -> 0.52401927 | H17: =INDEX('Market Data'!$B$33:$K$33,MATCH(H$4,'Market Data'!$B$24:$K$24,0)) -> 2.6219008 | I17: =INDEX('Market Data'!$B$33:$K$33,MATCH(I$4,'Market Data'!$B$24:$K$24,0)) -> 2.9806597 | ... K17: =INDEX('Market Data'!$B$33:$K$33,MATCH(K$4,'Market Data'!$B$24:$K$24,0)) -> 7.241931
A18: Book Value Per Share (Rp) | B18: =(INDEX('Balance Sheet'!$B$77:$K$77,MATCH(B$4,'Balance Sheet'!$B$4:$K$4,0))-INDEX('Balance Sheet'!$B$75:$K$75,MATCH(B$4,'Balance Sheet'!$B$4:$K$4,0)))/B6 -> 226.96078 | C18: =(INDEX('Balance Sheet'!$B$77:$K$77,MATCH(C$4,'Balance Sheet'!$B$4:$K$4,0))-INDEX('Balance Sheet'!$B$75:$K$75,MATCH(C$4,'Balance Sheet'!$B$4:$K$4,0)))/C6 -> 263.48039 | D18: =(INDEX('Balance Sheet'!$B$77:$K$77,MATCH(D$4,'Balance Sheet'!$B$4:$K$4,0))-INDEX('Balance Sheet'!$B$75:$K$75,MATCH(D$4,'Balance Sheet'!$B$4:$K$4,0)))/D6 -> 314.1844 | E18: =(INDEX('Balance Sheet'!$B$77:$K$77,MATCH(E$4,'Balance Sheet'!$B$4:$K$4,0))-INDEX('Balance Sheet'!$B$75:$K$75,MATCH(E$4,'Balance Sheet'!$B$4:$K$4,0)))/E6 -> 332.62411 | F18: =(INDEX('Balance Sheet'!$B$77:$K$77,MATCH(F$4,'Balance Sheet'!$B$4:$K$4,0))-INDEX('Balance Sheet'!$B$75:$K$75,MATCH(F$4,'Balance Sheet'!$B$4:$K$4,0)))/F6 -> 336.40662 | G18: =(INDEX('Balance Sheet'!$B$77:$K$77,MATCH(G$4,'Balance Sheet'!$B$4:$K$4,0))-INDEX('Balance Sheet'!$B$75:$K$75,MATCH(G$4,'Balance Sheet'!$B$4:$K$4,0)))/G6 -> 343.49882 | H18: =(INDEX('Balance Sheet'!$B$77:$K$77,MATCH(H$4,'Balance Sheet'!$B$4:$K$4,0))-INDEX('Balance Sheet'!$B$75:$K$75,MATCH(H$4,'Balance Sheet'!$B$4:$K$4,0)))/H6 -> 400.47281 | I18: =(INDEX('Balance Sheet'!$B$77:$K$77,MATCH(I$4,'Balance Sheet'!$B$4:$K$4,0))-INDEX('Balance Sheet'!$B$75:$K$75,MATCH(I$4,'Balance Sheet'!$B$4:$K$4,0)))/I6 -> 473.04965 | ... K18: =(INDEX('Balance Sheet'!$B$77:$K$77,MATCH(K$4,'Balance Sheet'!$B$4:$K$4,0))-INDEX('Balance Sheet'!$B$75:$K$75,MATCH(K$4,'Balance Sheet'!$B$4:$K$4,0)))/K6 -> 842.31678
A19: Price to Tangible Book Value (Annual) | B19: =INDEX('Market Data'!$B$34:$K$34,MATCH(B$4,'Market Data'!$B$24:$K$24,0)) -> 1.2769761 | C19: =INDEX('Market Data'!$B$34:$K$34,MATCH(C$4,'Market Data'!$B$24:$K$24,0)) -> 1.5598191 | D19: =INDEX('Market Data'!$B$34:$K$34,MATCH(D$4,'Market Data'!$B$24:$K$24,0)) -> 1.3481561 | E19: =INDEX('Market Data'!$B$34:$K$34,MATCH(E$4,'Market Data'!$B$24:$K$24,0)) -> 0.72466532 | F19: =INDEX('Market Data'!$B$34:$K$34,MATCH(F$4,'Market Data'!$B$24:$K$24,0)) -> 0.94240048 | G19: =INDEX('Market Data'!$B$34:$K$34,MATCH(G$4,'Market Data'!$B$24:$K$24,0)) -> 0.70028011 | H19: =INDEX('Market Data'!$B$34:$K$34,MATCH(H$4,'Market Data'!$B$24:$K$24,0)) -> 3.443865 | I19: =INDEX('Market Data'!$B$34:$K$34,MATCH(I$4,'Market Data'!$B$24:$K$24,0)) -> 3.719041 | ... K19: =INDEX('Market Data'!$B$34:$K$34,MATCH(K$4,'Market Data'!$B$24:$K$24,0)) -> 8.2436888
A20: Tangible Book Value Per Share (Rp) | B20: 156.62 | C20: 192.33 | D20: 241.07 | E20: 262.19 | F20: 265.28 | G20: 257.04 | H20: 304.89 | I20: 379.13 | J20: 448.22 | K20: 739.96
A22: STRUKTUR UTANG (DEBT)
A23: Short-term Debt (Annual) | B23: =INDEX('Balance Sheet'!$B$31:$K$31,MATCH(B$4,'Balance Sheet'!$B$4:$K$4,0))+INDEX('Balance Sheet'!$B$44:$K$44,MATCH(B$4,'Balance Sheet'!$B$4:$K$4,0))+INDEX('Balance Sheet'!$B$46:$K$46,MATCH(B$4,'Balance Sheet'!$B$4:$K$4,0)) -> 208 | C23: =INDEX('Balance Sheet'!$B$31:$K$31,MATCH(C$4,'Balance Sheet'!$B$4:$K$4,0))+INDEX('Balance Sheet'!$B$44:$K$44,MATCH(C$4,'Balance Sheet'!$B$4:$K$4,0))+INDEX('Balance Sheet'!$B$46:$K$46,MATCH(C$4,'Balance Sheet'!$B$4:$K$4,0)) -> 104 | D23: =INDEX('Balance Sheet'!$B$31:$K$31,MATCH(D$4,'Balance Sheet'!$B$4:$K$4,0))+INDEX('Balance Sheet'!$B$44:$K$44,MATCH(D$4,'Balance Sheet'!$B$4:$K$4,0))+INDEX('Balance Sheet'!$B$46:$K$46,MATCH(D$4,'Balance Sheet'!$B$4:$K$4,0)) -> 97 | E23: =INDEX('Balance Sheet'!$B$31:$K$31,MATCH(E$4,'Balance Sheet'!$B$4:$K$4,0))+INDEX('Balance Sheet'!$B$44:$K$44,MATCH(E$4,'Balance Sheet'!$B$4:$K$4,0))+INDEX('Balance Sheet'!$B$46:$K$46,MATCH(E$4,'Balance Sheet'!$B$4:$K$4,0)) -> 168 | F23: =INDEX('Balance Sheet'!$B$31:$K$31,MATCH(F$4,'Balance Sheet'!$B$4:$K$4,0))+INDEX('Balance Sheet'!$B$44:$K$44,MATCH(F$4,'Balance Sheet'!$B$4:$K$4,0))+INDEX('Balance Sheet'!$B$46:$K$46,MATCH(F$4,'Balance Sheet'!$B$4:$K$4,0)) -> 156 | G23: =INDEX('Balance Sheet'!$B$31:$K$31,MATCH(G$4,'Balance Sheet'!$B$4:$K$4,0))+INDEX('Balance Sheet'!$B$44:$K$44,MATCH(G$4,'Balance Sheet'!$B$4:$K$4,0))+INDEX('Balance Sheet'!$B$46:$K$46,MATCH(G$4,'Balance Sheet'!$B$4:$K$4,0)) -> 126 | H23: =INDEX('Balance Sheet'!$B$31:$K$31,MATCH(H$4,'Balance Sheet'!$B$4:$K$4,0))+INDEX('Balance Sheet'!$B$44:$K$44,MATCH(H$4,'Balance Sheet'!$B$4:$K$4,0))+INDEX('Balance Sheet'!$B$46:$K$46,MATCH(H$4,'Balance Sheet'!$B$4:$K$4,0)) -> 186 | I23: =INDEX('Balance Sheet'!$B$31:$K$31,MATCH(I$4,'Balance Sheet'!$B$4:$K$4,0))+INDEX('Balance Sheet'!$B$44:$K$44,MATCH(I$4,'Balance Sheet'!$B$4:$K$4,0))+INDEX('Balance Sheet'!$B$46:$K$46,MATCH(I$4,'Balance Sheet'!$B$4:$K$4,0)) -> 437 | ... K23: =INDEX('Balance Sheet'!$B$31:$K$31,MATCH(K$4,'Balance Sheet'!$B$4:$K$4,0))+INDEX('Balance Sheet'!$B$44:$K$44,MATCH(K$4,'Balance Sheet'!$B$4:$K$4,0))+INDEX('Balance Sheet'!$B$46:$K$46,MATCH(K$4,'Balance Sheet'!$B$4:$K$4,0)) -> 722
A24: Long-term Debt (Annual) | B24: =INDEX('Balance Sheet'!$B$55:$K$55,MATCH(B$4,'Balance Sheet'!$B$4:$K$4,0))+INDEX('Balance Sheet'!$B$57:$K$57,MATCH(B$4,'Balance Sheet'!$B$4:$K$4,0)) -> 396 | C24: =INDEX('Balance Sheet'!$B$55:$K$55,MATCH(C$4,'Balance Sheet'!$B$4:$K$4,0))+INDEX('Balance Sheet'!$B$57:$K$57,MATCH(C$4,'Balance Sheet'!$B$4:$K$4,0)) -> 96 | D24: =INDEX('Balance Sheet'!$B$55:$K$55,MATCH(D$4,'Balance Sheet'!$B$4:$K$4,0))+INDEX('Balance Sheet'!$B$57:$K$57,MATCH(D$4,'Balance Sheet'!$B$4:$K$4,0)) -> 582 | E24: =INDEX('Balance Sheet'!$B$55:$K$55,MATCH(E$4,'Balance Sheet'!$B$4:$K$4,0))+INDEX('Balance Sheet'!$B$57:$K$57,MATCH(E$4,'Balance Sheet'!$B$4:$K$4,0)) -> 454 | F24: =INDEX('Balance Sheet'!$B$55:$K$55,MATCH(F$4,'Balance Sheet'!$B$4:$K$4,0))+INDEX('Balance Sheet'!$B$57:$K$57,MATCH(F$4,'Balance Sheet'!$B$4:$K$4,0)) -> 283 | G24: =INDEX('Balance Sheet'!$B$55:$K$55,MATCH(G$4,'Balance Sheet'!$B$4:$K$4,0))+INDEX('Balance Sheet'!$B$57:$K$57,MATCH(G$4,'Balance Sheet'!$B$4:$K$4,0)) -> 1411 | H24: =INDEX('Balance Sheet'!$B$55:$K$55,MATCH(H$4,'Balance Sheet'!$B$4:$K$4,0))+INDEX('Balance Sheet'!$B$57:$K$57,MATCH(H$4,'Balance Sheet'!$B$4:$K$4,0)) -> 1534 | I24: =INDEX('Balance Sheet'!$B$55:$K$55,MATCH(I$4,'Balance Sheet'!$B$4:$K$4,0))+INDEX('Balance Sheet'!$B$57:$K$57,MATCH(I$4,'Balance Sheet'!$B$4:$K$4,0)) -> 1661 | ... K24: =INDEX('Balance Sheet'!$B$55:$K$55,MATCH(K$4,'Balance Sheet'!$B$4:$K$4,0))+INDEX('Balance Sheet'!$B$57:$K$57,MATCH(K$4,'Balance Sheet'!$B$4:$K$4,0)) -> 1825
A25: Total Debt (Annual) | B25: =B23+B24 -> 604 | C25: =C23+C24 -> 200 | D25: =D23+D24 -> 679 | E25: =E23+E24 -> 622 | F25: =F23+F24 -> 439 | G25: =G23+G24 -> 1537 | H25: =H23+H24 -> 1720 | I25: =I23+I24 -> 2098 | ... K25: =K23+K24 -> 2547
A26: Net Debt (Annual) | B26: =B25-INDEX('Balance Sheet'!$B$10:$K$10,MATCH(B$4,'Balance Sheet'!$B$4:$K$4,0)) -> 430 | C26: =C25-INDEX('Balance Sheet'!$B$10:$K$10,MATCH(C$4,'Balance Sheet'!$B$4:$K$4,0)) -> 26 | D26: =D25-INDEX('Balance Sheet'!$B$10:$K$10,MATCH(D$4,'Balance Sheet'!$B$4:$K$4,0)) -> 389 | E26: =E25-INDEX('Balance Sheet'!$B$10:$K$10,MATCH(E$4,'Balance Sheet'!$B$4:$K$4,0)) -> 318 | F26: =F25-INDEX('Balance Sheet'!$B$10:$K$10,MATCH(F$4,'Balance Sheet'!$B$4:$K$4,0)) -> -108 | G26: =G25-INDEX('Balance Sheet'!$B$10:$K$10,MATCH(G$4,'Balance Sheet'!$B$4:$K$4,0)) -> 982 | H26: =H25-INDEX('Balance Sheet'!$B$10:$K$10,MATCH(H$4,'Balance Sheet'!$B$4:$K$4,0)) -> 1251 | I26: =I25-INDEX('Balance Sheet'!$B$10:$K$10,MATCH(I$4,'Balance Sheet'!$B$4:$K$4,0)) -> 1560 | ... K26: =K25-INDEX('Balance Sheet'!$B$10:$K$10,MATCH(K$4,'Balance Sheet'!$B$4:$K$4,0)) -> 1028
A27: Working Capital (Annual) | B27: =INDEX('Balance Sheet'!$B$22:$K$22,MATCH(B$4,'Balance Sheet'!$B$4:$K$4,0))-INDEX('Balance Sheet'!$B$50:$K$50,MATCH(B$4,'Balance Sheet'!$B$4:$K$4,0)) -> 137 | C27: =INDEX('Balance Sheet'!$B$22:$K$22,MATCH(C$4,'Balance Sheet'!$B$4:$K$4,0))-INDEX('Balance Sheet'!$B$50:$K$50,MATCH(C$4,'Balance Sheet'!$B$4:$K$4,0)) -> 377 | D27: =INDEX('Balance Sheet'!$B$22:$K$22,MATCH(D$4,'Balance Sheet'!$B$4:$K$4,0))-INDEX('Balance Sheet'!$B$50:$K$50,MATCH(D$4,'Balance Sheet'!$B$4:$K$4,0)) -> 710 | E27: =INDEX('Balance Sheet'!$B$22:$K$22,MATCH(E$4,'Balance Sheet'!$B$4:$K$4,0))-INDEX('Balance Sheet'!$B$50:$K$50,MATCH(E$4,'Balance Sheet'!$B$4:$K$4,0)) -> 657 | F27: =INDEX('Balance Sheet'!$B$22:$K$22,MATCH(F$4,'Balance Sheet'!$B$4:$K$4,0))-INDEX('Balance Sheet'!$B$50:$K$50,MATCH(F$4,'Balance Sheet'!$B$4:$K$4,0)) -> 560 | G27: =INDEX('Balance Sheet'!$B$22:$K$22,MATCH(G$4,'Balance Sheet'!$B$4:$K$4,0))-INDEX('Balance Sheet'!$B$50:$K$50,MATCH(G$4,'Balance Sheet'!$B$4:$K$4,0)) -> 672 | H27: =INDEX('Balance Sheet'!$B$22:$K$22,MATCH(H$4,'Balance Sheet'!$B$4:$K$4,0))-INDEX('Balance Sheet'!$B$50:$K$50,MATCH(H$4,'Balance Sheet'!$B$4:$K$4,0)) -> 493 | I27: =INDEX('Balance Sheet'!$B$22:$K$22,MATCH(I$4,'Balance Sheet'!$B$4:$K$4,0))-INDEX('Balance Sheet'!$B$50:$K$50,MATCH(I$4,'Balance Sheet'!$B$4:$K$4,0)) -> 373 | ... K27: =INDEX('Balance Sheet'!$B$22:$K$22,MATCH(K$4,'Balance Sheet'!$B$4:$K$4,0))-INDEX('Balance Sheet'!$B$50:$K$50,MATCH(K$4,'Balance Sheet'!$B$4:$K$4,0)) -> 707
A29: RASIO LIKUIDITAS & LEVERAGE
A30: Current Ratio (Annual) | B30: =INDEX('Balance Sheet'!$B$22:$K$22,MATCH(B$4,'Balance Sheet'!$B$4:$K$4,0))/INDEX('Balance Sheet'!$B$50:$K$50,MATCH(B$4,'Balance Sheet'!$B$4:$K$4,0)) -> 1.4521452 | C30: =INDEX('Balance Sheet'!$B$22:$K$22,MATCH(C$4,'Balance Sheet'!$B$4:$K$4,0))/INDEX('Balance Sheet'!$B$50:$K$50,MATCH(C$4,'Balance Sheet'!$B$4:$K$4,0)) -> 2.2823129 | D30: =INDEX('Balance Sheet'!$B$22:$K$22,MATCH(D$4,'Balance Sheet'!$B$4:$K$4,0))/INDEX('Balance Sheet'!$B$50:$K$50,MATCH(D$4,'Balance Sheet'!$B$4:$K$4,0)) -> 3.751938 | E30: =INDEX('Balance Sheet'!$B$22:$K$22,MATCH(E$4,'Balance Sheet'!$B$4:$K$4,0))/INDEX('Balance Sheet'!$B$50:$K$50,MATCH(E$4,'Balance Sheet'!$B$4:$K$4,0)) -> 3.0091743 | F30: =INDEX('Balance Sheet'!$B$22:$K$22,MATCH(F$4,'Balance Sheet'!$B$4:$K$4,0))/INDEX('Balance Sheet'!$B$50:$K$50,MATCH(F$4,'Balance Sheet'!$B$4:$K$4,0)) -> 2.8181818 | G30: =INDEX('Balance Sheet'!$B$22:$K$22,MATCH(G$4,'Balance Sheet'!$B$4:$K$4,0))/INDEX('Balance Sheet'!$B$50:$K$50,MATCH(G$4,'Balance Sheet'!$B$4:$K$4,0)) -> 3.3914591 | H30: =INDEX('Balance Sheet'!$B$22:$K$22,MATCH(H$4,'Balance Sheet'!$B$4:$K$4,0))/INDEX('Balance Sheet'!$B$50:$K$50,MATCH(H$4,'Balance Sheet'!$B$4:$K$4,0)) -> 2.1710214 | I30: =INDEX('Balance Sheet'!$B$22:$K$22,MATCH(I$4,'Balance Sheet'!$B$4:$K$4,0))/INDEX('Balance Sheet'!$B$50:$K$50,MATCH(I$4,'Balance Sheet'!$B$4:$K$4,0)) -> 1.4287356 | ... K30: =INDEX('Balance Sheet'!$B$22:$K$22,MATCH(K$4,'Balance Sheet'!$B$4:$K$4,0))/INDEX('Balance Sheet'!$B$50:$K$50,MATCH(K$4,'Balance Sheet'!$B$4:$K$4,0)) -> 1.4435383
A31: Quick Ratio (Annual) | B31: =(INDEX('Balance Sheet'!$B$22:$K$22,MATCH(B$4,'Balance Sheet'!$B$4:$K$4,0))-INDEX('Balance Sheet'!$B$19:$K$19,MATCH(B$4,'Balance Sheet'!$B$4:$K$4,0)))/INDEX('Balance Sheet'!$B$50:$K$50,MATCH(B$4,'Balance Sheet'!$B$4:$K$4,0)) -> 1.2805281 | C31: =(INDEX('Balance Sheet'!$B$22:$K$22,MATCH(C$4,'Balance Sheet'!$B$4:$K$4,0))-INDEX('Balance Sheet'!$B$19:$K$19,MATCH(C$4,'Balance Sheet'!$B$4:$K$4,0)))/INDEX('Balance Sheet'!$B$50:$K$50,MATCH(C$4,'Balance Sheet'!$B$4:$K$4,0)) -> 1.9455782 | D31: =(INDEX('Balance Sheet'!$B$22:$K$22,MATCH(D$4,'Balance Sheet'!$B$4:$K$4,0))-INDEX('Balance Sheet'!$B$19:$K$19,MATCH(D$4,'Balance Sheet'!$B$4:$K$4,0)))/INDEX('Balance Sheet'!$B$50:$K$50,MATCH(D$4,'Balance Sheet'!$B$4:$K$4,0)) -> 3.744186 | E31: =(INDEX('Balance Sheet'!$B$22:$K$22,MATCH(E$4,'Balance Sheet'!$B$4:$K$4,0))-INDEX('Balance Sheet'!$B$19:$K$19,MATCH(E$4,'Balance Sheet'!$B$4:$K$4,0)))/INDEX('Balance Sheet'!$B$50:$K$50,MATCH(E$4,'Balance Sheet'!$B$4:$K$4,0)) -> 3.0030581 | F31: =(INDEX('Balance Sheet'!$B$22:$K$22,MATCH(F$4,'Balance Sheet'!$B$4:$K$4,0))-INDEX('Balance Sheet'!$B$19:$K$19,MATCH(F$4,'Balance Sheet'!$B$4:$K$4,0)))/INDEX('Balance Sheet'!$B$50:$K$50,MATCH(F$4,'Balance Sheet'!$B$4:$K$4,0)) -> 2.8051948 | G31: =(INDEX('Balance Sheet'!$B$22:$K$22,MATCH(G$4,'Balance Sheet'!$B$4:$K$4,0))-INDEX('Balance Sheet'!$B$19:$K$19,MATCH(G$4,'Balance Sheet'!$B$4:$K$4,0)))/INDEX('Balance Sheet'!$B$50:$K$50,MATCH(G$4,'Balance Sheet'!$B$4:$K$4,0)) -> 3.366548 | H31: =(INDEX('Balance Sheet'!$B$22:$K$22,MATCH(H$4,'Balance Sheet'!$B$4:$K$4,0))-INDEX('Balance Sheet'!$B$19:$K$19,MATCH(H$4,'Balance Sheet'!$B$4:$K$4,0)))/INDEX('Balance Sheet'!$B$50:$K$50,MATCH(H$4,'Balance Sheet'!$B$4:$K$4,0)) -> 2.1425178 | I31: =(INDEX('Balance Sheet'!$B$22:$K$22,MATCH(I$4,'Balance Sheet'!$B$4:$K$4,0))-INDEX('Balance Sheet'!$B$19:$K$19,MATCH(I$4,'Balance Sheet'!$B$4:$K$4,0)))/INDEX('Balance Sheet'!$B$50:$K$50,MATCH(I$4,'Balance Sheet'!$B$4:$K$4,0)) -> 1.416092 | ... K31: =(INDEX('Balance Sheet'!$B$22:$K$22,MATCH(K$4,'Balance Sheet'!$B$4:$K$4,0))-INDEX('Balance Sheet'!$B$19:$K$19,MATCH(K$4,'Balance Sheet'!$B$4:$K$4,0)))/INDEX('Balance Sheet'!$B$50:$K$50,MATCH(K$4,'Balance Sheet'!$B$4:$K$4,0)) -> 1.4366374
A32: Debt to Equity Ratio (Annual) | B32: =B25/(INDEX('Balance Sheet'!$B$77:$K$77,MATCH(B$4,'Balance Sheet'!$B$4:$K$4,0))-INDEX('Balance Sheet'!$B$75:$K$75,MATCH(B$4,'Balance Sheet'!$B$4:$K$4,0))) -> 0.65226782 | C32: =C25/(INDEX('Balance Sheet'!$B$77:$K$77,MATCH(C$4,'Balance Sheet'!$B$4:$K$4,0))-INDEX('Balance Sheet'!$B$75:$K$75,MATCH(C$4,'Balance Sheet'!$B$4:$K$4,0))) -> 0.18604651 | D32: =D25/(INDEX('Balance Sheet'!$B$77:$K$77,MATCH(D$4,'Balance Sheet'!$B$4:$K$4,0))-INDEX('Balance Sheet'!$B$75:$K$75,MATCH(D$4,'Balance Sheet'!$B$4:$K$4,0))) -> 0.51091046 | E32: =E25/(INDEX('Balance Sheet'!$B$77:$K$77,MATCH(E$4,'Balance Sheet'!$B$4:$K$4,0))-INDEX('Balance Sheet'!$B$75:$K$75,MATCH(E$4,'Balance Sheet'!$B$4:$K$4,0))) -> 0.44207534 | F32: =F25/(INDEX('Balance Sheet'!$B$77:$K$77,MATCH(F$4,'Balance Sheet'!$B$4:$K$4,0))-INDEX('Balance Sheet'!$B$75:$K$75,MATCH(F$4,'Balance Sheet'!$B$4:$K$4,0))) -> 0.30850316 | G32: =G25/(INDEX('Balance Sheet'!$B$77:$K$77,MATCH(G$4,'Balance Sheet'!$B$4:$K$4,0))-INDEX('Balance Sheet'!$B$75:$K$75,MATCH(G$4,'Balance Sheet'!$B$4:$K$4,0))) -> 1.0578114 | H32: =H25/(INDEX('Balance Sheet'!$B$77:$K$77,MATCH(H$4,'Balance Sheet'!$B$4:$K$4,0))-INDEX('Balance Sheet'!$B$75:$K$75,MATCH(H$4,'Balance Sheet'!$B$4:$K$4,0))) -> 1.0153483 | I32: =I25/(INDEX('Balance Sheet'!$B$77:$K$77,MATCH(I$4,'Balance Sheet'!$B$4:$K$4,0))-INDEX('Balance Sheet'!$B$75:$K$75,MATCH(I$4,'Balance Sheet'!$B$4:$K$4,0))) -> 1.0484758 | ... K32: =K25/(INDEX('Balance Sheet'!$B$77:$K$77,MATCH(K$4,'Balance Sheet'!$B$4:$K$4,0))-INDEX('Balance Sheet'!$B$75:$K$75,MATCH(K$4,'Balance Sheet'!$B$4:$K$4,0))) -> 0.71484704
A33: Financial Leverage (Annual) | B33: =INDEX('Balance Sheet'!$B$26:$K$26,MATCH(B$4,'Balance Sheet'!$B$4:$K$4,0))/(INDEX('Balance Sheet'!$B$77:$K$77,MATCH(B$4,'Balance Sheet'!$B$4:$K$4,0))-INDEX('Balance Sheet'!$B$75:$K$75,MATCH(B$4,'Balance Sheet'!$B$4:$K$4,0))) -> 2.1069114 | C33: =INDEX('Balance Sheet'!$B$26:$K$26,MATCH(C$4,'Balance Sheet'!$B$4:$K$4,0))/(INDEX('Balance Sheet'!$B$77:$K$77,MATCH(C$4,'Balance Sheet'!$B$4:$K$4,0))-INDEX('Balance Sheet'!$B$75:$K$75,MATCH(C$4,'Balance Sheet'!$B$4:$K$4,0))) -> 1.8967442 | D33: =INDEX('Balance Sheet'!$B$26:$K$26,MATCH(D$4,'Balance Sheet'!$B$4:$K$4,0))/(INDEX('Balance Sheet'!$B$77:$K$77,MATCH(D$4,'Balance Sheet'!$B$4:$K$4,0))-INDEX('Balance Sheet'!$B$75:$K$75,MATCH(D$4,'Balance Sheet'!$B$4:$K$4,0))) -> 2.0820166 | E33: =INDEX('Balance Sheet'!$B$26:$K$26,MATCH(E$4,'Balance Sheet'!$B$4:$K$4,0))/(INDEX('Balance Sheet'!$B$77:$K$77,MATCH(E$4,'Balance Sheet'!$B$4:$K$4,0))-INDEX('Balance Sheet'!$B$75:$K$75,MATCH(E$4,'Balance Sheet'!$B$4:$K$4,0))) -> 1.782516 | F33: =INDEX('Balance Sheet'!$B$26:$K$26,MATCH(F$4,'Balance Sheet'!$B$4:$K$4,0))/(INDEX('Balance Sheet'!$B$77:$K$77,MATCH(F$4,'Balance Sheet'!$B$4:$K$4,0))-INDEX('Balance Sheet'!$B$75:$K$75,MATCH(F$4,'Balance Sheet'!$B$4:$K$4,0))) -> 1.6521434 | G33: =INDEX('Balance Sheet'!$B$26:$K$26,MATCH(G$4,'Balance Sheet'!$B$4:$K$4,0))/(INDEX('Balance Sheet'!$B$77:$K$77,MATCH(G$4,'Balance Sheet'!$B$4:$K$4,0))-INDEX('Balance Sheet'!$B$75:$K$75,MATCH(G$4,'Balance Sheet'!$B$4:$K$4,0))) -> 2.4129387 | H33: =INDEX('Balance Sheet'!$B$26:$K$26,MATCH(H$4,'Balance Sheet'!$B$4:$K$4,0))/(INDEX('Balance Sheet'!$B$77:$K$77,MATCH(H$4,'Balance Sheet'!$B$4:$K$4,0))-INDEX('Balance Sheet'!$B$75:$K$75,MATCH(H$4,'Balance Sheet'!$B$4:$K$4,0))) -> 2.3978749 | I33: =INDEX('Balance Sheet'!$B$26:$K$26,MATCH(I$4,'Balance Sheet'!$B$4:$K$4,0))/(INDEX('Balance Sheet'!$B$77:$K$77,MATCH(I$4,'Balance Sheet'!$B$4:$K$4,0))-INDEX('Balance Sheet'!$B$75:$K$75,MATCH(I$4,'Balance Sheet'!$B$4:$K$4,0))) -> 2.5357321 | ... K33: =INDEX('Balance Sheet'!$B$26:$K$26,MATCH(K$4,'Balance Sheet'!$B$4:$K$4,0))/(INDEX('Balance Sheet'!$B$77:$K$77,MATCH(K$4,'Balance Sheet'!$B$4:$K$4,0))-INDEX('Balance Sheet'!$B$75:$K$75,MATCH(K$4,'Balance Sheet'!$B$4:$K$4,0))) -> 2.2413696
A34: LT Debt/Equity (Annual) | B34: =B24/(INDEX('Balance Sheet'!$B$77:$K$77,MATCH(B$4,'Balance Sheet'!$B$4:$K$4,0))-INDEX('Balance Sheet'!$B$75:$K$75,MATCH(B$4,'Balance Sheet'!$B$4:$K$4,0))) -> 0.42764579 | C34: =C24/(INDEX('Balance Sheet'!$B$77:$K$77,MATCH(C$4,'Balance Sheet'!$B$4:$K$4,0))-INDEX('Balance Sheet'!$B$75:$K$75,MATCH(C$4,'Balance Sheet'!$B$4:$K$4,0))) -> 0.089302326 | D34: =D24/(INDEX('Balance Sheet'!$B$77:$K$77,MATCH(D$4,'Balance Sheet'!$B$4:$K$4,0))-INDEX('Balance Sheet'!$B$75:$K$75,MATCH(D$4,'Balance Sheet'!$B$4:$K$4,0))) -> 0.43792325 | E34: =E24/(INDEX('Balance Sheet'!$B$77:$K$77,MATCH(E$4,'Balance Sheet'!$B$4:$K$4,0))-INDEX('Balance Sheet'!$B$75:$K$75,MATCH(E$4,'Balance Sheet'!$B$4:$K$4,0))) -> 0.32267235 | F34: =F24/(INDEX('Balance Sheet'!$B$77:$K$77,MATCH(F$4,'Balance Sheet'!$B$4:$K$4,0))-INDEX('Balance Sheet'!$B$75:$K$75,MATCH(F$4,'Balance Sheet'!$B$4:$K$4,0))) -> 0.19887561 | G34: =G24/(INDEX('Balance Sheet'!$B$77:$K$77,MATCH(G$4,'Balance Sheet'!$B$4:$K$4,0))-INDEX('Balance Sheet'!$B$75:$K$75,MATCH(G$4,'Balance Sheet'!$B$4:$K$4,0))) -> 0.97109429 | H34: =H24/(INDEX('Balance Sheet'!$B$77:$K$77,MATCH(H$4,'Balance Sheet'!$B$4:$K$4,0))-INDEX('Balance Sheet'!$B$75:$K$75,MATCH(H$4,'Balance Sheet'!$B$4:$K$4,0))) -> 0.905549 | I34: =I24/(INDEX('Balance Sheet'!$B$77:$K$77,MATCH(I$4,'Balance Sheet'!$B$4:$K$4,0))-INDEX('Balance Sheet'!$B$75:$K$75,MATCH(I$4,'Balance Sheet'!$B$4:$K$4,0))) -> 0.83008496 | ... K34: =K24/(INDEX('Balance Sheet'!$B$77:$K$77,MATCH(K$4,'Balance Sheet'!$B$4:$K$4,0))-INDEX('Balance Sheet'!$B$75:$K$75,MATCH(K$4,'Balance Sheet'!$B$4:$K$4,0))) -> 0.51220881
A35: LT Debt/Total Assets (Annual) | B35: =B24/INDEX('Balance Sheet'!$B$26:$K$26,MATCH(B$4,'Balance Sheet'!$B$4:$K$4,0)) -> 0.20297283 | C35: =C24/INDEX('Balance Sheet'!$B$26:$K$26,MATCH(C$4,'Balance Sheet'!$B$4:$K$4,0)) -> 0.047081903 | D35: =D24/INDEX('Balance Sheet'!$B$26:$K$26,MATCH(D$4,'Balance Sheet'!$B$4:$K$4,0)) -> 0.2103361 | E35: =E24/INDEX('Balance Sheet'!$B$26:$K$26,MATCH(E$4,'Balance Sheet'!$B$4:$K$4,0)) -> 0.18102073 | F35: =F24/INDEX('Balance Sheet'!$B$26:$K$26,MATCH(F$4,'Balance Sheet'!$B$4:$K$4,0)) -> 0.12037431 | G35: =G24/INDEX('Balance Sheet'!$B$26:$K$26,MATCH(G$4,'Balance Sheet'!$B$4:$K$4,0)) -> 0.40245294 | H35: =H24/INDEX('Balance Sheet'!$B$26:$K$26,MATCH(H$4,'Balance Sheet'!$B$4:$K$4,0)) -> 0.37764648 | I35: =I24/INDEX('Balance Sheet'!$B$26:$K$26,MATCH(I$4,'Balance Sheet'!$B$4:$K$4,0)) -> 0.32735514 | ... K35: =K24/INDEX('Balance Sheet'!$B$26:$K$26,MATCH(K$4,'Balance Sheet'!$B$4:$K$4,0)) -> 0.22852492
A36: Net Debt/Total Equity (Annual) | B36: =B26/(INDEX('Balance Sheet'!$B$77:$K$77,MATCH(B$4,'Balance Sheet'!$B$4:$K$4,0))-INDEX('Balance Sheet'!$B$75:$K$75,MATCH(B$4,'Balance Sheet'!$B$4:$K$4,0))) -> 0.46436285 | C36: =C26/(INDEX('Balance Sheet'!$B$77:$K$77,MATCH(C$4,'Balance Sheet'!$B$4:$K$4,0))-INDEX('Balance Sheet'!$B$75:$K$75,MATCH(C$4,'Balance Sheet'!$B$4:$K$4,0))) -> 0.024186047 | D36: =D26/(INDEX('Balance Sheet'!$B$77:$K$77,MATCH(D$4,'Balance Sheet'!$B$4:$K$4,0))-INDEX('Balance Sheet'!$B$75:$K$75,MATCH(D$4,'Balance Sheet'!$B$4:$K$4,0))) -> 0.29270128 | E36: =E26/(INDEX('Balance Sheet'!$B$77:$K$77,MATCH(E$4,'Balance Sheet'!$B$4:$K$4,0))-INDEX('Balance Sheet'!$B$75:$K$75,MATCH(E$4,'Balance Sheet'!$B$4:$K$4,0))) -> 0.22601279 | F36: =F26/(INDEX('Balance Sheet'!$B$77:$K$77,MATCH(F$4,'Balance Sheet'!$B$4:$K$4,0))-INDEX('Balance Sheet'!$B$75:$K$75,MATCH(F$4,'Balance Sheet'!$B$4:$K$4,0))) -> -0.075895994 | G36: =G26/(INDEX('Balance Sheet'!$B$77:$K$77,MATCH(G$4,'Balance Sheet'!$B$4:$K$4,0))-INDEX('Balance Sheet'!$B$75:$K$75,MATCH(G$4,'Balance Sheet'!$B$4:$K$4,0))) -> 0.67584308 | H36: =H26/(INDEX('Balance Sheet'!$B$77:$K$77,MATCH(H$4,'Balance Sheet'!$B$4:$K$4,0))-INDEX('Balance Sheet'!$B$75:$K$75,MATCH(H$4,'Balance Sheet'!$B$4:$K$4,0))) -> 0.73848878 | I36: =I26/(INDEX('Balance Sheet'!$B$77:$K$77,MATCH(I$4,'Balance Sheet'!$B$4:$K$4,0))-INDEX('Balance Sheet'!$B$75:$K$75,MATCH(I$4,'Balance Sheet'!$B$4:$K$4,0))) -> 0.77961019 | ... K36: =K26/(INDEX('Balance Sheet'!$B$77:$K$77,MATCH(K$4,'Balance Sheet'!$B$4:$K$4,0))-INDEX('Balance Sheet'!$B$75:$K$75,MATCH(K$4,'Balance Sheet'!$B$4:$K$4,0))) -> 0.28852091
A37: Total Debt/Total Assets (Annual) | B37: =B25/INDEX('Balance Sheet'!$B$26:$K$26,MATCH(B$4,'Balance Sheet'!$B$4:$K$4,0)) -> 0.30958483 | C37: =C25/INDEX('Balance Sheet'!$B$26:$K$26,MATCH(C$4,'Balance Sheet'!$B$4:$K$4,0)) -> 0.098087298 | D37: =D25/INDEX('Balance Sheet'!$B$26:$K$26,MATCH(D$4,'Balance Sheet'!$B$4:$K$4,0)) -> 0.24539212 | E37: =E25/INDEX('Balance Sheet'!$B$26:$K$26,MATCH(E$4,'Balance Sheet'!$B$4:$K$4,0)) -> 0.24800638 | F37: =F25/INDEX('Balance Sheet'!$B$26:$K$26,MATCH(F$4,'Balance Sheet'!$B$4:$K$4,0)) -> 0.18672905 | G37: =G25/INDEX('Balance Sheet'!$B$26:$K$26,MATCH(G$4,'Balance Sheet'!$B$4:$K$4,0)) -> 0.43839133 | H37: =H25/INDEX('Balance Sheet'!$B$26:$K$26,MATCH(H$4,'Balance Sheet'!$B$4:$K$4,0)) -> 0.42343673 | I37: =I25/INDEX('Balance Sheet'!$B$26:$K$26,MATCH(I$4,'Balance Sheet'!$B$4:$K$4,0)) -> 0.41348049 | ... K37: =K25/INDEX('Balance Sheet'!$B$26:$K$26,MATCH(K$4,'Balance Sheet'!$B$4:$K$4,0)) -> 0.31893313
A38: Total Liabilities/Equity (Annual) | B38: =INDEX('Balance Sheet'!$B$65:$K$65,MATCH(B$4,'Balance Sheet'!$B$4:$K$4,0))/(INDEX('Balance Sheet'!$B$77:$K$77,MATCH(B$4,'Balance Sheet'!$B$4:$K$4,0))-INDEX('Balance Sheet'!$B$75:$K$75,MATCH(B$4,'Balance Sheet'!$B$4:$K$4,0))) -> 0.77969762 | C38: =INDEX('Balance Sheet'!$B$65:$K$65,MATCH(C$4,'Balance Sheet'!$B$4:$K$4,0))/(INDEX('Balance Sheet'!$B$77:$K$77,MATCH(C$4,'Balance Sheet'!$B$4:$K$4,0))-INDEX('Balance Sheet'!$B$75:$K$75,MATCH(C$4,'Balance Sheet'!$B$4:$K$4,0))) -> 0.38139535 | D38: =INDEX('Balance Sheet'!$B$65:$K$65,MATCH(D$4,'Balance Sheet'!$B$4:$K$4,0))/(INDEX('Balance Sheet'!$B$77:$K$77,MATCH(D$4,'Balance Sheet'!$B$4:$K$4,0))-INDEX('Balance Sheet'!$B$75:$K$75,MATCH(D$4,'Balance Sheet'!$B$4:$K$4,0))) -> 0.64635064 | E38: =INDEX('Balance Sheet'!$B$65:$K$65,MATCH(E$4,'Balance Sheet'!$B$4:$K$4,0))/(INDEX('Balance Sheet'!$B$77:$K$77,MATCH(E$4,'Balance Sheet'!$B$4:$K$4,0))-INDEX('Balance Sheet'!$B$75:$K$75,MATCH(E$4,'Balance Sheet'!$B$4:$K$4,0))) -> 0.57071784 | F38: =INDEX('Balance Sheet'!$B$65:$K$65,MATCH(F$4,'Balance Sheet'!$B$4:$K$4,0))/(INDEX('Balance Sheet'!$B$77:$K$77,MATCH(F$4,'Balance Sheet'!$B$4:$K$4,0))-INDEX('Balance Sheet'!$B$75:$K$75,MATCH(F$4,'Balance Sheet'!$B$4:$K$4,0))) -> 0.4300773 | G38: =INDEX('Balance Sheet'!$B$65:$K$65,MATCH(G$4,'Balance Sheet'!$B$4:$K$4,0))/(INDEX('Balance Sheet'!$B$77:$K$77,MATCH(G$4,'Balance Sheet'!$B$4:$K$4,0))-INDEX('Balance Sheet'!$B$75:$K$75,MATCH(G$4,'Balance Sheet'!$B$4:$K$4,0))) -> 1.1837577 | H38: =INDEX('Balance Sheet'!$B$65:$K$65,MATCH(H$4,'Balance Sheet'!$B$4:$K$4,0))/(INDEX('Balance Sheet'!$B$77:$K$77,MATCH(H$4,'Balance Sheet'!$B$4:$K$4,0))-INDEX('Balance Sheet'!$B$75:$K$75,MATCH(H$4,'Balance Sheet'!$B$4:$K$4,0))) -> 1.1729634 | I38: =INDEX('Balance Sheet'!$B$65:$K$65,MATCH(I$4,'Balance Sheet'!$B$4:$K$4,0))/(INDEX('Balance Sheet'!$B$77:$K$77,MATCH(I$4,'Balance Sheet'!$B$4:$K$4,0))-INDEX('Balance Sheet'!$B$75:$K$75,MATCH(I$4,'Balance Sheet'!$B$4:$K$4,0))) -> 1.3433283 | ... K38: =INDEX('Balance Sheet'!$B$65:$K$65,MATCH(K$4,'Balance Sheet'!$B$4:$K$4,0))/(INDEX('Balance Sheet'!$B$77:$K$77,MATCH(K$4,'Balance Sheet'!$B$4:$K$4,0))-INDEX('Balance Sheet'!$B$75:$K$75,MATCH(K$4,'Balance Sheet'!$B$4:$K$4,0))) -> 1.0404154
A40: RASIO EFISIENSI (ACTIVITY)
A41: Days Sales Outstanding (Annual) | B41: =(INDEX('Balance Sheet'!$B$14:$K$14,MATCH(B$4,'Balance Sheet'!$B$4:$K$4,0))/INDEX('Income Statement'!$B$5:$K$5,MATCH(B$4,'Income Statement'!$B$4:$K$4,0)))*365 -> 18.345396 | C41: =(AVERAGE(INDEX('Balance Sheet'!$B$14:$K$14,MATCH(C$4,'Balance Sheet'!$B$4:$K$4,0)),INDEX('Balance Sheet'!$B$14:$K$14,MATCH(B$4,'Balance Sheet'!$B$4:$K$4,0)))/INDEX('Income Statement'!$B$5:$K$5,MATCH(C$4,'Income Statement'!$B$4:$K$4,0)))*365 -> 35.437782 | D41: =(AVERAGE(INDEX('Balance Sheet'!$B$14:$K$14,MATCH(D$4,'Balance Sheet'!$B$4:$K$4,0)),INDEX('Balance Sheet'!$B$14:$K$14,MATCH(C$4,'Balance Sheet'!$B$4:$K$4,0)))/INDEX('Income Statement'!$B$5:$K$5,MATCH(D$4,'Income Statement'!$B$4:$K$4,0)))*365 -> 50.8571 | E41: =(AVERAGE(INDEX('Balance Sheet'!$B$14:$K$14,MATCH(E$4,'Balance Sheet'!$B$4:$K$4,0)),INDEX('Balance Sheet'!$B$14:$K$14,MATCH(D$4,'Balance Sheet'!$B$4:$K$4,0)))/INDEX('Income Statement'!$B$5:$K$5,MATCH(E$4,'Income Statement'!$B$4:$K$4,0)))*365 -> 44.463252 | F41: =(AVERAGE(INDEX('Balance Sheet'!$B$14:$K$14,MATCH(F$4,'Balance Sheet'!$B$4:$K$4,0)),INDEX('Balance Sheet'!$B$14:$K$14,MATCH(E$4,'Balance Sheet'!$B$4:$K$4,0)))/INDEX('Income Statement'!$B$5:$K$5,MATCH(F$4,'Income Statement'!$B$4:$K$4,0)))*365 -> 46.131944 | G41: =(AVERAGE(INDEX('Balance Sheet'!$B$14:$K$14,MATCH(G$4,'Balance Sheet'!$B$4:$K$4,0)),INDEX('Balance Sheet'!$B$14:$K$14,MATCH(F$4,'Balance Sheet'!$B$4:$K$4,0)))/INDEX('Income Statement'!$B$5:$K$5,MATCH(G$4,'Income Statement'!$B$4:$K$4,0)))*365 -> 42.215302 | H41: =(AVERAGE(INDEX('Balance Sheet'!$B$14:$K$14,MATCH(H$4,'Balance Sheet'!$B$4:$K$4,0)),INDEX('Balance Sheet'!$B$14:$K$14,MATCH(G$4,'Balance Sheet'!$B$4:$K$4,0)))/INDEX('Income Statement'!$B$5:$K$5,MATCH(H$4,'Income Statement'!$B$4:$K$4,0)))*365 -> 41.6313 | I41: =(AVERAGE(INDEX('Balance Sheet'!$B$14:$K$14,MATCH(I$4,'Balance Sheet'!$B$4:$K$4,0)),INDEX('Balance Sheet'!$B$14:$K$14,MATCH(H$4,'Balance Sheet'!$B$4:$K$4,0)))/INDEX('Income Statement'!$B$5:$K$5,MATCH(I$4,'Income Statement'!$B$4:$K$4,0)))*365 -> 42.630309 | J41: =(AVERAGE(INDEX('Balance Sheet'!$B$14:$K$14,MATCH(J$4,'Balance Sheet'!$B$4:$K$4,0)),INDEX('Balance Sheet'!$B$14:$K$14,MATCH(I$4,'Balance Sheet'!$B$4:$K$4,0)))/INDEX('Income Statement'!$B$5:$K$5,MATCH(J$4,'Income Statement'!$B$4:$K$4,0)))*365 -> 45.839945 | K41: =(AVERAGE(INDEX('Balance Sheet'!$B$14:$K$14,MATCH(K$4,'Balance Sheet'!$B$4:$K$4,0)),INDEX('Balance Sheet'!$B$14:$K$14,MATCH(J$4,'Balance Sheet'!$B$4:$K$4,0)))/INDEX('Income Statement'!$B$5:$K$5,MATCH(K$4,'Income Statement'!$B$4:$K$4,0)))*365 -> 45.396563
A42: Days Inventory (Annual) | B42: =(INDEX('Balance Sheet'!$B$19:$K$19,MATCH(B$4,'Balance Sheet'!$B$4:$K$4,0))/ABS(INDEX('Income Statement'!$B$6:$K$6,MATCH(B$4,'Income Statement'!$B$4:$K$4,0))))*365 -> 8.7667436 | C42: =(AVERAGE(INDEX('Balance Sheet'!$B$19:$K$19,MATCH(C$4,'Balance Sheet'!$B$4:$K$4,0)),INDEX('Balance Sheet'!$B$19:$K$19,MATCH(B$4,'Balance Sheet'!$B$4:$K$4,0)))/ABS(INDEX('Income Statement'!$B$6:$K$6,MATCH(C$4,'Income Statement'!$B$4:$K$4,0))))*365 -> 16.551051 | D42: =(AVERAGE(INDEX('Balance Sheet'!$B$19:$K$19,MATCH(D$4,'Balance Sheet'!$B$4:$K$4,0)),INDEX('Balance Sheet'!$B$19:$K$19,MATCH(C$4,'Balance Sheet'!$B$4:$K$4,0)))/ABS(INDEX('Income Statement'!$B$6:$K$6,MATCH(D$4,'Income Statement'!$B$4:$K$4,0))))*365 -> 13.251258 | E42: =(AVERAGE(INDEX('Balance Sheet'!$B$19:$K$19,MATCH(E$4,'Balance Sheet'!$B$4:$K$4,0)),INDEX('Balance Sheet'!$B$19:$K$19,MATCH(D$4,'Balance Sheet'!$B$4:$K$4,0)))/ABS(INDEX('Income Statement'!$B$6:$K$6,MATCH(E$4,'Income Statement'!$B$4:$K$4,0))))*365 -> 0.49125168 | F42: =(AVERAGE(INDEX('Balance Sheet'!$B$19:$K$19,MATCH(F$4,'Balance Sheet'!$B$4:$K$4,0)),INDEX('Balance Sheet'!$B$19:$K$19,MATCH(E$4,'Balance Sheet'!$B$4:$K$4,0)))/ABS(INDEX('Income Statement'!$B$6:$K$6,MATCH(F$4,'Income Statement'!$B$4:$K$4,0))))*365 -> 0.90871369 | G42: =(AVERAGE(INDEX('Balance Sheet'!$B$19:$K$19,MATCH(G$4,'Balance Sheet'!$B$4:$K$4,0)),INDEX('Balance Sheet'!$B$19:$K$19,MATCH(F$4,'Balance Sheet'!$B$4:$K$4,0)))/ABS(INDEX('Income Statement'!$B$6:$K$6,MATCH(G$4,'Income Statement'!$B$4:$K$4,0))))*365 -> 1.6955236 | H42: =(AVERAGE(INDEX('Balance Sheet'!$B$19:$K$19,MATCH(H$4,'Balance Sheet'!$B$4:$K$4,0)),INDEX('Balance Sheet'!$B$19:$K$19,MATCH(G$4,'Balance Sheet'!$B$4:$K$4,0)))/ABS(INDEX('Income Statement'!$B$6:$K$6,MATCH(H$4,'Income Statement'!$B$4:$K$4,0))))*365 -> 2.2933201 | I42: =(AVERAGE(INDEX('Balance Sheet'!$B$19:$K$19,MATCH(I$4,'Balance Sheet'!$B$4:$K$4,0)),INDEX('Balance Sheet'!$B$19:$K$19,MATCH(H$4,'Balance Sheet'!$B$4:$K$4,0)))/ABS(INDEX('Income Statement'!$B$6:$K$6,MATCH(I$4,'Income Statement'!$B$4:$K$4,0))))*365 -> 1.9969077 | J42: =(AVERAGE(INDEX('Balance Sheet'!$B$19:$K$19,MATCH(J$4,'Balance Sheet'!$B$4:$K$4,0)),INDEX('Balance Sheet'!$B$19:$K$19,MATCH(I$4,'Balance Sheet'!$B$4:$K$4,0)))/ABS(INDEX('Income Statement'!$B$6:$K$6,MATCH(J$4,'Income Statement'!$B$4:$K$4,0))))*365 -> 1.243188 | K42: =(AVERAGE(INDEX('Balance Sheet'!$B$19:$K$19,MATCH(K$4,'Balance Sheet'!$B$4:$K$4,0)),INDEX('Balance Sheet'!$B$19:$K$19,MATCH(J$4,'Balance Sheet'!$B$4:$K$4,0)))/ABS(INDEX('Income Statement'!$B$6:$K$6,MATCH(K$4,'Income Statement'!$B$4:$K$4,0))))*365 -> 1.1388456
A43: Payables Period (Annual) | B43: =(INDEX('Balance Sheet'!$B$35:$K$35,MATCH(B$4,'Balance Sheet'!$B$4:$K$4,0))/ABS(INDEX('Income Statement'!$B$6:$K$6,MATCH(B$4,'Income Statement'!$B$4:$K$4,0))))*365 -> 10.95843 | C43: =(AVERAGE(INDEX('Balance Sheet'!$B$35:$K$35,MATCH(C$4,'Balance Sheet'!$B$4:$K$4,0)),INDEX('Balance Sheet'!$B$35:$K$35,MATCH(B$4,'Balance Sheet'!$B$4:$K$4,0)))/ABS(INDEX('Income Statement'!$B$6:$K$6,MATCH(C$4,'Income Statement'!$B$4:$K$4,0))))*365 -> 20.606607 | D43: =(AVERAGE(INDEX('Balance Sheet'!$B$35:$K$35,MATCH(D$4,'Balance Sheet'!$B$4:$K$4,0)),INDEX('Balance Sheet'!$B$35:$K$35,MATCH(C$4,'Balance Sheet'!$B$4:$K$4,0)))/ABS(INDEX('Income Statement'!$B$6:$K$6,MATCH(D$4,'Income Statement'!$B$4:$K$4,0))))*365 -> 31.094536 | E43: =(AVERAGE(INDEX('Balance Sheet'!$B$35:$K$35,MATCH(E$4,'Balance Sheet'!$B$4:$K$4,0)),INDEX('Balance Sheet'!$B$35:$K$35,MATCH(D$4,'Balance Sheet'!$B$4:$K$4,0)))/ABS(INDEX('Income Statement'!$B$6:$K$6,MATCH(E$4,'Income Statement'!$B$4:$K$4,0))))*365 -> 29.352288 | F43: =(AVERAGE(INDEX('Balance Sheet'!$B$35:$K$35,MATCH(F$4,'Balance Sheet'!$B$4:$K$4,0)),INDEX('Balance Sheet'!$B$35:$K$35,MATCH(E$4,'Balance Sheet'!$B$4:$K$4,0)))/ABS(INDEX('Income Statement'!$B$6:$K$6,MATCH(F$4,'Income Statement'!$B$4:$K$4,0))))*365 -> 34.834025 | G43: =(AVERAGE(INDEX('Balance Sheet'!$B$35:$K$35,MATCH(G$4,'Balance Sheet'!$B$4:$K$4,0)),INDEX('Balance Sheet'!$B$35:$K$35,MATCH(F$4,'Balance Sheet'!$B$4:$K$4,0)))/ABS(INDEX('Income Statement'!$B$6:$K$6,MATCH(G$4,'Income Statement'!$B$4:$K$4,0))))*365 -> 32.985642 | H43: =(AVERAGE(INDEX('Balance Sheet'!$B$35:$K$35,MATCH(H$4,'Balance Sheet'!$B$4:$K$4,0)),INDEX('Balance Sheet'!$B$35:$K$35,MATCH(G$4,'Balance Sheet'!$B$4:$K$4,0)))/ABS(INDEX('Income Statement'!$B$6:$K$6,MATCH(H$4,'Income Statement'!$B$4:$K$4,0))))*365 -> 33.434193 | I43: =(AVERAGE(INDEX('Balance Sheet'!$B$35:$K$35,MATCH(I$4,'Balance Sheet'!$B$4:$K$4,0)),INDEX('Balance Sheet'!$B$35:$K$35,MATCH(H$4,'Balance Sheet'!$B$4:$K$4,0)))/ABS(INDEX('Income Statement'!$B$6:$K$6,MATCH(I$4,'Income Statement'!$B$4:$K$4,0))))*365 -> 40.19862 | J43: =(AVERAGE(INDEX('Balance Sheet'!$B$35:$K$35,MATCH(J$4,'Balance Sheet'!$B$4:$K$4,0)),INDEX('Balance Sheet'!$B$35:$K$35,MATCH(I$4,'Balance Sheet'!$B$4:$K$4,0)))/ABS(INDEX('Income Statement'!$B$6:$K$6,MATCH(J$4,'Income Statement'!$B$4:$K$4,0))))*365 -> 36.922684 | K43: =(AVERAGE(INDEX('Balance Sheet'!$B$35:$K$35,MATCH(K$4,'Balance Sheet'!$B$4:$K$4,0)),INDEX('Balance Sheet'!$B$35:$K$35,MATCH(J$4,'Balance Sheet'!$B$4:$K$4,0)))/ABS(INDEX('Income Statement'!$B$6:$K$6,MATCH(K$4,'Income Statement'!$B$4:$K$4,0))))*365 -> 42.080343
A44: Cash Conversion Cycle (Annual) | B44: =B41+B42-B43 -> 16.15371 | C44: =C41+C42-C43 -> 31.382227 | D44: =D41+D42-D43 -> 33.013822 | E44: =E41+E42-E43 -> 15.602216 | F44: =F41+F42-F43 -> 12.206633 | G44: =G41+G42-G43 -> 10.925184 | H44: =H41+H42-H43 -> 10.490427 | I44: =I41+I42-I43 -> 4.4285962 | ... K44: =K41+K42-K43 -> 4.4550658
A45: Receivables Turnover (Annual) | B45: =365/B41 -> 19.896 | C45: =365/C41 -> 10.299742 | D45: =365/D41 -> 7.1769723 | E45: =365/E41 -> 8.2090261 | F45: =365/F41 -> 7.9120879 | G45: =365/G41 -> 8.6461538 | H45: =365/H41 -> 8.7674419 | I45: =365/I41 -> 8.5619835 | ... K45: =365/K41 -> 8.0402562
A46: Inventory Turnover (Annual) | B46: =365/B42 -> 41.634615 | C46: =365/C42 -> 22.05298 | D46: =365/D42 -> 27.544554 | E46: =365/E42 -> 743 | F46: =365/F42 -> 401.66667 | G46: =365/G42 -> 215.27273 | H46: =365/H42 -> 159.15789 | I46: =365/I42 -> 182.78261 | ... K46: =365/K42 -> 320.5
A47: Fixed Assets Turnover (Annual) | B47: 3.42 | C47: 2.31 | D47: 2.07 | E47: 2.16 | F47: 1.86 | G47: 1.11 | H47: 0.94 | I47: 1.28 | J47: 1.51 | K47: 1.45
A48: Asset Turnover (Annual) | B48: =INDEX('Income Statement'!$B$5:$K$5,MATCH(B$4,'Income Statement'!$B$4:$K$4,0))/INDEX('Balance Sheet'!$B$26:$K$26,MATCH(B$4,'Balance Sheet'!$B$4:$K$4,0)) -> 1.2747309 | C48: =INDEX('Income Statement'!$B$5:$K$5,MATCH(C$4,'Income Statement'!$B$4:$K$4,0))/AVERAGE(INDEX('Balance Sheet'!$B$26:$K$26,MATCH(C$4,'Balance Sheet'!$B$4:$K$4,0)),INDEX('Balance Sheet'!$B$26:$K$26,MATCH(B$4,'Balance Sheet'!$B$4:$K$4,0))) -> 0.99899749 | D48: =INDEX('Income Statement'!$B$5:$K$5,MATCH(D$4,'Income Statement'!$B$4:$K$4,0))/AVERAGE(INDEX('Balance Sheet'!$B$26:$K$26,MATCH(D$4,'Balance Sheet'!$B$4:$K$4,0)),INDEX('Balance Sheet'!$B$26:$K$26,MATCH(C$4,'Balance Sheet'!$B$4:$K$4,0))) -> 0.70037453 | E48: =INDEX('Income Statement'!$B$5:$K$5,MATCH(E$4,'Income Statement'!$B$4:$K$4,0))/AVERAGE(INDEX('Balance Sheet'!$B$26:$K$26,MATCH(E$4,'Balance Sheet'!$B$4:$K$4,0)),INDEX('Balance Sheet'!$B$26:$K$26,MATCH(D$4,'Balance Sheet'!$B$4:$K$4,0))) -> 0.65516588 | F48: =INDEX('Income Statement'!$B$5:$K$5,MATCH(F$4,'Income Statement'!$B$4:$K$4,0))/AVERAGE(INDEX('Balance Sheet'!$B$26:$K$26,MATCH(F$4,'Balance Sheet'!$B$4:$K$4,0)),INDEX('Balance Sheet'!$B$26:$K$26,MATCH(E$4,'Balance Sheet'!$B$4:$K$4,0))) -> 0.59271455 | G48: =INDEX('Income Statement'!$B$5:$K$5,MATCH(G$4,'Income Statement'!$B$4:$K$4,0))/AVERAGE(INDEX('Balance Sheet'!$B$26:$K$26,MATCH(G$4,'Balance Sheet'!$B$4:$K$4,0)),INDEX('Balance Sheet'!$B$26:$K$26,MATCH(F$4,'Balance Sheet'!$B$4:$K$4,0))) -> 0.4797678 | H48: =INDEX('Income Statement'!$B$5:$K$5,MATCH(H$4,'Income Statement'!$B$4:$K$4,0))/AVERAGE(INDEX('Balance Sheet'!$B$26:$K$26,MATCH(H$4,'Balance Sheet'!$B$4:$K$4,0)),INDEX('Balance Sheet'!$B$26:$K$26,MATCH(G$4,'Balance Sheet'!$B$4:$K$4,0))) -> 0.49815011 | I48: =INDEX('Income Statement'!$B$5:$K$5,MATCH(I$4,'Income Statement'!$B$4:$K$4,0))/AVERAGE(INDEX('Balance Sheet'!$B$26:$K$26,MATCH(I$4,'Balance Sheet'!$B$4:$K$4,0)),INDEX('Balance Sheet'!$B$26:$K$26,MATCH(H$4,'Balance Sheet'!$B$4:$K$4,0))) -> 0.68038529 | J48: =INDEX('Income Statement'!$B$5:$K$5,MATCH(J$4,'Income Statement'!$B$4:$K$4,0))/AVERAGE(INDEX('Balance Sheet'!$B$26:$K$26,MATCH(J$4,'Balance Sheet'!$B$4:$K$4,0)),INDEX('Balance Sheet'!$B$26:$K$26,MATCH(I$4,'Balance Sheet'!$B$4:$K$4,0))) -> 0.77349444 | K48: =INDEX('Income Statement'!$B$5:$K$5,MATCH(K$4,'Income Statement'!$B$4:$K$4,0))/AVERAGE(INDEX('Balance Sheet'!$B$26:$K$26,MATCH(K$4,'Balance Sheet'!$B$4:$K$4,0)),INDEX('Balance Sheet'!$B$26:$K$26,MATCH(J$4,'Balance Sheet'!$B$4:$K$4,0))) -> 0.65877061
A49: Working Capital Turnover (Annual) | B49: =INDEX('Income Statement'!$B$5:$K$5,MATCH(B$4,'Income Statement'!$B$4:$K$4,0))/B27 -> 18.153285 | C49: =INDEX('Income Statement'!$B$5:$K$5,MATCH(C$4,'Income Statement'!$B$4:$K$4,0))/C27 -> 5.2864721 | D49: =INDEX('Income Statement'!$B$5:$K$5,MATCH(D$4,'Income Statement'!$B$4:$K$4,0))/D27 -> 2.3704225 | E49: =INDEX('Income Statement'!$B$5:$K$5,MATCH(E$4,'Income Statement'!$B$4:$K$4,0))/E27 -> 2.630137 | F49: =INDEX('Income Statement'!$B$5:$K$5,MATCH(F$4,'Income Statement'!$B$4:$K$4,0))/F27 -> 2.5714286 | G49: =INDEX('Income Statement'!$B$5:$K$5,MATCH(G$4,'Income Statement'!$B$4:$K$4,0))/G27 -> 2.0907738 | H49: =INDEX('Income Statement'!$B$5:$K$5,MATCH(H$4,'Income Statement'!$B$4:$K$4,0))/H27 -> 3.8235294 | I49: =INDEX('Income Statement'!$B$5:$K$5,MATCH(I$4,'Income Statement'!$B$4:$K$4,0))/I27 -> 8.3324397 | ... K49: =INDEX('Income Statement'!$B$5:$K$5,MATCH(K$4,'Income Statement'!$B$4:$K$4,0))/K27 -> 6.2149929
A50: Working Capital Ratio (Annual) | B50: =B30 -> 1.4521452 | C50: =C30 -> 2.2823129 | D50: =D30 -> 3.751938 | E50: =E30 -> 3.0091743 | F50: =F30 -> 2.8181818 | G50: =G30 -> 3.3914591 | H50: =H30 -> 2.1710214 | I50: =I30 -> 1.4287356 | ... K50: =K30 -> 1.4435383
A52: ARUS KAS KUNCI
A53: Operating Cash Flow (Annual) | B53: =INDEX('Cash Flow'!$B$18:$K$18,MATCH(B$4,'Cash Flow'!$B$4:$K$4,0)) -> 151 | C53: =INDEX('Cash Flow'!$B$18:$K$18,MATCH(C$4,'Cash Flow'!$B$4:$K$4,0)) -> -115 | D53: =INDEX('Cash Flow'!$B$18:$K$18,MATCH(D$4,'Cash Flow'!$B$4:$K$4,0)) -> 154 | E53: =INDEX('Cash Flow'!$B$18:$K$18,MATCH(E$4,'Cash Flow'!$B$4:$K$4,0)) -> 66 | F53: =INDEX('Cash Flow'!$B$18:$K$18,MATCH(F$4,'Cash Flow'!$B$4:$K$4,0)) -> 241 | G53: =INDEX('Cash Flow'!$B$18:$K$18,MATCH(G$4,'Cash Flow'!$B$4:$K$4,0)) -> -51 | H53: =INDEX('Cash Flow'!$B$18:$K$18,MATCH(H$4,'Cash Flow'!$B$4:$K$4,0)) -> 184 | I53: =INDEX('Cash Flow'!$B$18:$K$18,MATCH(I$4,'Cash Flow'!$B$4:$K$4,0)) -> 674 | ... K53: =INDEX('Cash Flow'!$B$18:$K$18,MATCH(K$4,'Cash Flow'!$B$4:$K$4,0)) -> 883
A54: Capital Expenditure (Annual) | B54: =INDEX('Cash Flow'!$B$21:$K$21,MATCH(B$4,'Cash Flow'!$B$4:$K$4,0)) -> -154 | C54: =INDEX('Cash Flow'!$B$21:$K$21,MATCH(C$4,'Cash Flow'!$B$4:$K$4,0)) -> -11 | D54: =INDEX('Cash Flow'!$B$21:$K$21,MATCH(D$4,'Cash Flow'!$B$4:$K$4,0)) -> -13 | E54: =INDEX('Cash Flow'!$B$21:$K$21,MATCH(E$4,'Cash Flow'!$B$4:$K$4,0)) -> -137 | F54: =INDEX('Cash Flow'!$B$21:$K$21,MATCH(F$4,'Cash Flow'!$B$4:$K$4,0)) -> -28 | G54: =INDEX('Cash Flow'!$B$21:$K$21,MATCH(G$4,'Cash Flow'!$B$4:$K$4,0)) -> -995 | H54: =INDEX('Cash Flow'!$B$21:$K$21,MATCH(H$4,'Cash Flow'!$B$4:$K$4,0)) -> -335 | I54: =INDEX('Cash Flow'!$B$21:$K$21,MATCH(I$4,'Cash Flow'!$B$4:$K$4,0)) -> -538 | ... K54: =INDEX('Cash Flow'!$B$21:$K$21,MATCH(K$4,'Cash Flow'!$B$4:$K$4,0)) -> -745
A55: Free Cash Flow (Annual) | B55: =B53+B54 -> -3 | C55: =C53+C54 -> -126 | D55: =D53+D54 -> 141 | E55: =E53+E54 -> -71 | F55: =F53+F54 -> 213 | G55: =G53+G54 -> -1046 | H55: =H53+H54 -> -151 | I55: =I53+I54 -> 136 | ... K55: =K53+K54 -> 138
A56: Free Cash Flow Per Share (Rp) | B56: =B55/B6 -> -0.73529412 | C56: =C55/C6 -> -30.882353 | D56: =D55/D6 -> 33.333333 | E56: =E55/E6 -> -16.78487 | F56: =F55/F6 -> 50.35461 | G56: =G55/G6 -> -247.28132 | H56: =H55/H6 -> -35.6974 | I56: =I55/I6 -> 32.1513 | ... K56: =K55/K6 -> 32.624113

Sheet Market Data
A1: MARKET DATA - PT Rukun Raharja Tbk (RAJA)
A4: Category | B4: Item | C4: Value
A5: General | B5: Company | C5: PT Rukun Raharja Tbk
A6: General | B6: Ticker | C6: RAJA
A7: General | B7: Sector | C7: Energi
A8: General | B8: Industry | C8: Minyak & Gas - Layanan Terintegrasi (Midstream/Trading Gas, Pembangkit Listrik)
A9: Market | B9: Current Price | C9: 890
A10: Market | B10: Share Outstanding (Miliar Lembar) | C10: 21.14
A11: Market | B11: Market Cap (Miliar Rp) | C11: =C9*C10 -> 18814.6
A12: Market | B12: Enterprise Value (Miliar Rp) | C12: =C11+'Key Ratio'!K25-'Balance Sheet'!K10 -> 19842.6
A13: Market | B13: Beta | C13: 2.86
A14: Market | B14: Free Float (%)
A15: Market | B15: Dividend Yield (%)
A16: Market | B16: 52 Week High
A17: Market | B17: 52 Week Low
A18: Market | B18: Average Volume
A19: Market | B19: Last Updated | C19: 1 Agustus 2026
A23: HISTORIS HARGA SAHAM & VALUASI PASAR (12M 2016 - 12M 2025)
A24: Keterangan | B24: 12M 2016 | C24: 12M 2017 | D24: 12M 2018 | E24: 12M 2019 | F24: 12M 2020 | G24: 12M 2021 | H24: 12M 2022 | I24: 12M 2023 | J24: 12M 2024 | K24: 12M 2025
A25: Harga Saham / Price (Rp) | B25: 200 | C25: 300 | D25: 325 | E25: 190 | F25: 250 | G25: 180 | H25: 1050 | I25: 1410 | J25: 2725 | K25: 6100
A26: Share Outstanding (Miliar Lembar) | B26: ='Key Ratio'!B6 -> 4.08 | C26: ='Key Ratio'!C6 -> 4.08 | D26: ='Key Ratio'!D6 -> 4.23 | E26: ='Key Ratio'!E6 -> 4.23 | F26: ='Key Ratio'!F6 -> 4.23 | G26: ='Key Ratio'!G6 -> 4.23 | H26: ='Key Ratio'!H6 -> 4.23 | I26: ='Key Ratio'!I6 -> 4.23 | ... K26: ='Key Ratio'!K6 -> 4.23
A27: Market Cap (Miliar Rp) | B27: =B25*B26 -> 816 | C27: =C25*C26 -> 1224 | D27: =D25*D26 -> 1374.75 | E27: =E25*E26 -> 803.7 | F27: =F25*F26 -> 1057.5 | G27: =G25*G26 -> 761.4 | H27: =H25*H26 -> 4441.5 | I27: =I25*I26 -> 5964.3 | ... K27: =K25*K26 -> 25803
A28: Total Debt (Miliar Rp) | B28: ='Key Ratio'!B25 -> 604 | C28: ='Key Ratio'!C25 -> 200 | D28: ='Key Ratio'!D25 -> 679 | E28: ='Key Ratio'!E25 -> 622 | F28: ='Key Ratio'!F25 -> 439 | G28: ='Key Ratio'!G25 -> 1537 | H28: ='Key Ratio'!H25 -> 1720 | I28: ='Key Ratio'!I25 -> 2098 | ... K28: ='Key Ratio'!K25 -> 2547
A29: Kas Dan Setara Kas (Miliar Rp) | B29: =INDEX('Balance Sheet'!$B$10:$K$10,MATCH(B$24,'Balance Sheet'!$B$4:$K$4,0)) -> 174 | C29: =INDEX('Balance Sheet'!$B$10:$K$10,MATCH(C$24,'Balance Sheet'!$B$4:$K$4,0)) -> 174 | D29: =INDEX('Balance Sheet'!$B$10:$K$10,MATCH(D$24,'Balance Sheet'!$B$4:$K$4,0)) -> 290 | E29: =INDEX('Balance Sheet'!$B$10:$K$10,MATCH(E$24,'Balance Sheet'!$B$4:$K$4,0)) -> 304 | F29: =INDEX('Balance Sheet'!$B$10:$K$10,MATCH(F$24,'Balance Sheet'!$B$4:$K$4,0)) -> 547 | G29: =INDEX('Balance Sheet'!$B$10:$K$10,MATCH(G$24,'Balance Sheet'!$B$4:$K$4,0)) -> 555 | H29: =INDEX('Balance Sheet'!$B$10:$K$10,MATCH(H$24,'Balance Sheet'!$B$4:$K$4,0)) -> 469 | I29: =INDEX('Balance Sheet'!$B$10:$K$10,MATCH(I$24,'Balance Sheet'!$B$4:$K$4,0)) -> 538 | ... K29: =INDEX('Balance Sheet'!$B$10:$K$10,MATCH(K$24,'Balance Sheet'!$B$4:$K$4,0)) -> 1519
A30: Enterprise Value (Miliar Rp) | B30: =B27+B28-B29 -> 1246 | C30: =C27+C28-C29 -> 1250 | D30: =D27+D28-D29 -> 1763.75 | E30: =E27+E28-E29 -> 1121.7 | F30: =F27+F28-F29 -> 949.5 | G30: =G27+G28-G29 -> 1743.4 | H30: =H27+H28-H29 -> 5692.5 | I30: =I27+I28-I29 -> 7524.3 | ... K30: =K27+K28-K29 -> 26831
A31: PE Ratio (x) | B31: =B25/'Key Ratio'!B7 -> 9.3793103 | C31: =C25/'Key Ratio'!C7 -> 7.8461538 | D31: =D25/'Key Ratio'!D7 -> 8.4340491 | E31: =E25/'Key Ratio'!E7 -> 9.9222222 | F31: =F25/'Key Ratio'!F7 -> 52.875 | G31: =G25/'Key Ratio'!G7 -> 23.79375 | H31: =H25/'Key Ratio'!H7 -> 33.90458 | I31: =I25/'Key Ratio'!I7 -> 15.253964 | ... K31: =K25/'Key Ratio'!K7 -> 57.467706
A32: Price to Sales (x) | B32: =B27/INDEX('Income Statement'!$B$5:$K$5,MATCH(B$24,'Income Statement'!$B$4:$K$4,0)) -> 0.32810615 | C32: =C27/INDEX('Income Statement'!$B$5:$K$5,MATCH(C$24,'Income Statement'!$B$4:$K$4,0)) -> 0.61414952 | D32: =D27/INDEX('Income Statement'!$B$5:$K$5,MATCH(D$24,'Income Statement'!$B$4:$K$4,0)) -> 0.81684492 | E32: =E27/INDEX('Income Statement'!$B$5:$K$5,MATCH(E$24,'Income Statement'!$B$4:$K$4,0)) -> 0.46510417 | F32: =F27/INDEX('Income Statement'!$B$5:$K$5,MATCH(F$24,'Income Statement'!$B$4:$K$4,0)) -> 0.734375 | G32: =G27/INDEX('Income Statement'!$B$5:$K$5,MATCH(G$24,'Income Statement'!$B$4:$K$4,0)) -> 0.54192171 | H32: =H27/INDEX('Income Statement'!$B$5:$K$5,MATCH(H$24,'Income Statement'!$B$4:$K$4,0)) -> 2.3562334 | I32: =I27/INDEX('Income Statement'!$B$5:$K$5,MATCH(I$24,'Income Statement'!$B$4:$K$4,0)) -> 1.9190154 | ... K32: =K27/INDEX('Income Statement'!$B$5:$K$5,MATCH(K$24,'Income Statement'!$B$4:$K$4,0)) -> 5.8723259
A33: Price to Book Value (x) | B33: =B25/'Key Ratio'!B18 -> 0.8812095 | C33: =C25/'Key Ratio'!C18 -> 1.1386047 | D33: =D25/'Key Ratio'!D18 -> 1.0344244 | E33: =E25/'Key Ratio'!E18 -> 0.57121535 | F33: =F25/'Key Ratio'!F18 -> 0.74314828 | G33: =G25/'Key Ratio'!G18 -> 0.52401927 | H33: =H25/'Key Ratio'!H18 -> 2.6219008 | I33: =I25/'Key Ratio'!I18 -> 2.9806597 | ... K33: =K25/'Key Ratio'!K18 -> 7.241931
A34: Price to Tangible Book Value (x) | B34: =B25/'Key Ratio'!B20 -> 1.2769761 | C34: =C25/'Key Ratio'!C20 -> 1.5598191 | D34: =D25/'Key Ratio'!D20 -> 1.3481561 | E34: =E25/'Key Ratio'!E20 -> 0.72466532 | F34: =F25/'Key Ratio'!F20 -> 0.94240048 | G34: =G25/'Key Ratio'!G20 -> 0.70028011 | H34: =H25/'Key Ratio'!H20 -> 3.443865 | I34: =I25/'Key Ratio'!I20 -> 3.719041 | ... K34: =K25/'Key Ratio'!K20 -> 8.2436888

Sheet Forecast
A1: FORECAST 5 TAHUN - PT Rukun Raharja Tbk (RAJA)
A4: Keterangan | B4: 12M 2026F | C4: 12M 2027F | D4: 12M 2028F | E4: 12M 2029F | F4: 12M 2030F
A5: Pertumbuhan Pendapatan (%) | B5: =B68 -> 0.21182566 | C5: =('Income Statement'!$K$5/'Income Statement'!$H$5)^(1/3)-1 -> 0.32591668 | D5: =('Income Statement'!$K$5/'Income Statement'!$H$5)^(1/3)-1 -> 0.32591668 | E5: =('Income Statement'!$K$5/'Income Statement'!$H$5)^(1/3)-1 -> 0.32591668 | F5: =('Income Statement'!$K$5/'Income Statement'!$H$5)^(1/3)-1 -> 0.32591668
A6: Margin Laba Kotor (%) | B6: =AVERAGE('Income Statement'!$I$7/'Income Statement'!$I$5,'Income Statement'!$J$7/'Income Statement'!$J$5,'Income Statement'!$K$7/'Income Statement'!$K$5) -> 0.28876101 | C6: =AVERAGE('Income Statement'!$I$7/'Income Statement'!$I$5,'Income Statement'!$J$7/'Income Statement'!$J$5,'Income Statement'!$K$7/'Income Statement'!$K$5) -> 0.28876101 | D6: =AVERAGE('Income Statement'!$I$7/'Income Statement'!$I$5,'Income Statement'!$J$7/'Income Statement'!$J$5,'Income Statement'!$K$7/'Income Statement'!$K$5) -> 0.28876101 | E6: =AVERAGE('Income Statement'!$I$7/'Income Statement'!$I$5,'Income Statement'!$J$7/'Income Statement'!$J$5,'Income Statement'!$K$7/'Income Statement'!$K$5) -> 0.28876101 | F6: =AVERAGE('Income Statement'!$I$7/'Income Statement'!$I$5,'Income Statement'!$J$7/'Income Statement'!$J$5,'Income Statement'!$K$7/'Income Statement'!$K$5) -> 0.28876101
A7: Beban Usaha (% Pendapatan) | B7: =AVERAGE(ABS('Income Statement'!$I$8)/'Income Statement'!$I$5,ABS('Income Statement'!$J$8)/'Income Statement'!$J$5,ABS('Income Statement'!$K$8)/'Income Statement'!$K$5) -> 0.086948535 | C7: =AVERAGE(ABS('Income Statement'!$I$8)/'Income Statement'!$I$5,ABS('Income Statement'!$J$8)/'Income Statement'!$J$5,ABS('Income Statement'!$K$8)/'Income Statement'!$K$5) -> 0.086948535 | D7: =AVERAGE(ABS('Income Statement'!$I$8)/'Income Statement'!$I$5,ABS('Income Statement'!$J$8)/'Income Statement'!$J$5,ABS('Income Statement'!$K$8)/'Income Statement'!$K$5) -> 0.086948535 | E7: =AVERAGE(ABS('Income Statement'!$I$8)/'Income Statement'!$I$5,ABS('Income Statement'!$J$8)/'Income Statement'!$J$5,ABS('Income Statement'!$K$8)/'Income Statement'!$K$5) -> 0.086948535 | F7: =AVERAGE(ABS('Income Statement'!$I$8)/'Income Statement'!$I$5,ABS('Income Statement'!$J$8)/'Income Statement'!$J$5,ABS('Income Statement'!$K$8)/'Income Statement'!$K$5) -> 0.086948535
A8: Pertumbuhan Bagian Atas Hasil Bersih Entitas Asosiasi (%) | B8: =B5 -> 0.21182566 | C8: =C5 -> 0.32591668 | D8: =D5 -> 0.32591668 | E8: =E5 -> 0.32591668 | F8: =F5 -> 0.32591668
A9: Tingkat Bunga Efektif Atas Utang (%) | B9: =AVERAGE(ABS('Income Statement'!$I$14)/'Key Ratio'!$I$25,ABS('Income Statement'!$J$14)/'Key Ratio'!$J$25,ABS('Income Statement'!$K$14)/'Key Ratio'!$K$25) -> 0.073756823 | C9: =AVERAGE(ABS('Income Statement'!$I$14)/'Key Ratio'!$I$25,ABS('Income Statement'!$J$14)/'Key Ratio'!$J$25,ABS('Income Statement'!$K$14)/'Key Ratio'!$K$25) -> 0.073756823 | D9: =AVERAGE(ABS('Income Statement'!$I$14)/'Key Ratio'!$I$25,ABS('Income Statement'!$J$14)/'Key Ratio'!$J$25,ABS('Income Statement'!$K$14)/'Key Ratio'!$K$25) -> 0.073756823 | E9: =AVERAGE(ABS('Income Statement'!$I$14)/'Key Ratio'!$I$25,ABS('Income Statement'!$J$14)/'Key Ratio'!$J$25,ABS('Income Statement'!$K$14)/'Key Ratio'!$K$25) -> 0.073756823 | F9: =AVERAGE(ABS('Income Statement'!$I$14)/'Key Ratio'!$I$25,ABS('Income Statement'!$J$14)/'Key Ratio'!$J$25,ABS('Income Statement'!$K$14)/'Key Ratio'!$K$25) -> 0.073756823
A10: Tarif Pajak Efektif (%) | B10: =AVERAGE(ABS('Income Statement'!$I$21)/'Income Statement'!$I$20,ABS('Income Statement'!$J$21)/'Income Statement'!$J$20,ABS('Income Statement'!$K$21)/'Income Statement'!$K$20) -> 0.32249078 | C10: =AVERAGE(ABS('Income Statement'!$I$21)/'Income Statement'!$I$20,ABS('Income Statement'!$J$21)/'Income Statement'!$J$20,ABS('Income Statement'!$K$21)/'Income Statement'!$K$20) -> 0.32249078 | D10: =AVERAGE(ABS('Income Statement'!$I$21)/'Income Statement'!$I$20,ABS('Income Statement'!$J$21)/'Income Statement'!$J$20,ABS('Income Statement'!$K$21)/'Income Statement'!$K$20) -> 0.32249078 | E10: =AVERAGE(ABS('Income Statement'!$I$21)/'Income Statement'!$I$20,ABS('Income Statement'!$J$21)/'Income Statement'!$J$20,ABS('Income Statement'!$K$21)/'Income Statement'!$K$20) -> 0.32249078 | F10: =AVERAGE(ABS('Income Statement'!$I$21)/'Income Statement'!$I$20,ABS('Income Statement'!$J$21)/'Income Statement'!$J$20,ABS('Income Statement'!$K$21)/'Income Statement'!$K$20) -> 0.32249078
A11: Persentase Laba Bersih Milik Pemilik Entitas Induk (%) | B11: =AVERAGE('Income Statement'!$I$30/'Income Statement'!$I$25,'Income Statement'!$J$30/'Income Statement'!$J$25,'Income Statement'!$K$30/'Income Statement'!$K$25) -> 0.8670441 | C11: =AVERAGE('Income Statement'!$I$30/'Income Statement'!$I$25,'Income Statement'!$J$30/'Income Statement'!$J$25,'Income Statement'!$K$30/'Income Statement'!$K$25) -> 0.8670441 | D11: =AVERAGE('Income Statement'!$I$30/'Income Statement'!$I$25,'Income Statement'!$J$30/'Income Statement'!$J$25,'Income Statement'!$K$30/'Income Statement'!$K$25) -> 0.8670441 | E11: =AVERAGE('Income Statement'!$I$30/'Income Statement'!$I$25,'Income Statement'!$J$30/'Income Statement'!$J$25,'Income Statement'!$K$30/'Income Statement'!$K$25) -> 0.8670441 | F11: =AVERAGE('Income Statement'!$I$30/'Income Statement'!$I$25,'Income Statement'!$J$30/'Income Statement'!$J$25,'Income Statement'!$K$30/'Income Statement'!$K$25) -> 0.8670441
A12: Rasio Pembayaran Dividen (% Dari Laba Bersih Pemilik Tahun Sebelumnya) | B12: =AVERAGE(ABS('Cash Flow'!$B$49)/'Income Statement'!$J$30,ABS('Cash Flow'!$C$49)/'Income Statement'!$I$30) -> 0.51703767 | C12: =AVERAGE(ABS('Cash Flow'!$B$49)/'Income Statement'!$J$30,ABS('Cash Flow'!$C$49)/'Income Statement'!$I$30) -> 0.51703767 | D12: =AVERAGE(ABS('Cash Flow'!$B$49)/'Income Statement'!$J$30,ABS('Cash Flow'!$C$49)/'Income Statement'!$I$30) -> 0.51703767 | E12: =AVERAGE(ABS('Cash Flow'!$B$49)/'Income Statement'!$J$30,ABS('Cash Flow'!$C$49)/'Income Statement'!$I$30) -> 0.51703767 | F12: =AVERAGE(ABS('Cash Flow'!$B$49)/'Income Statement'!$J$30,ABS('Cash Flow'!$C$49)/'Income Statement'!$I$30) -> 0.51703767
A13: Belanja Modal / Capex (% Pendapatan) | B13: =AVERAGE(ABS('Cash Flow'!$B$21)/'Income Statement'!$K$5,ABS('Cash Flow'!$C$21)/'Income Statement'!$J$5,ABS('Cash Flow'!$D$21)/'Income Statement'!$I$5) -> 0.12777186 | C13: =AVERAGE(ABS('Cash Flow'!$B$21)/'Income Statement'!$K$5,ABS('Cash Flow'!$C$21)/'Income Statement'!$J$5,ABS('Cash Flow'!$D$21)/'Income Statement'!$I$5) -> 0.12777186 | D13: =AVERAGE(ABS('Cash Flow'!$B$21)/'Income Statement'!$K$5,ABS('Cash Flow'!$C$21)/'Income Statement'!$J$5,ABS('Cash Flow'!$D$21)/'Income Statement'!$I$5) -> 0.12777186 | E13: =AVERAGE(ABS('Cash Flow'!$B$21)/'Income Statement'!$K$5,ABS('Cash Flow'!$C$21)/'Income Statement'!$J$5,ABS('Cash Flow'!$D$21)/'Income Statement'!$I$5) -> 0.12777186 | F13: =AVERAGE(ABS('Cash Flow'!$B$21)/'Income Statement'!$K$5,ABS('Cash Flow'!$C$21)/'Income Statement'!$J$5,ABS('Cash Flow'!$D$21)/'Income Statement'!$I$5) -> 0.12777186
A14: Arus Kas Operasi / OCF (% Pendapatan) | B14: =AVERAGE('Key Ratio'!$I$53/'Income Statement'!$I$5,'Key Ratio'!$J$53/'Income Statement'!$J$5,'Key Ratio'!$K$53/'Income Statement'!$K$5) -> 0.20316143 | C14: =AVERAGE('Key Ratio'!$I$53/'Income Statement'!$I$5,'Key Ratio'!$J$53/'Income Statement'!$J$5,'Key Ratio'!$K$53/'Income Statement'!$K$5) -> 0.20316143 | D14: =AVERAGE('Key Ratio'!$I$53/'Income Statement'!$I$5,'Key Ratio'!$J$53/'Income Statement'!$J$5,'Key Ratio'!$K$53/'Income Statement'!$K$5) -> 0.20316143 | E14: =AVERAGE('Key Ratio'!$I$53/'Income Statement'!$I$5,'Key Ratio'!$J$53/'Income Statement'!$J$5,'Key Ratio'!$K$53/'Income Statement'!$K$5) -> 0.20316143 | F14: =AVERAGE('Key Ratio'!$I$53/'Income Statement'!$I$5,'Key Ratio'!$J$53/'Income Statement'!$J$5,'Key Ratio'!$K$53/'Income Statement'!$K$5) -> 0.20316143
A15: Pertumbuhan Total Debt (%) | B15: 0 | C15: 0 | D15: 0 | E15: 0 | F15: 0
A16: Asumsi Perputaran Aset / Asset Turnover (x) | B16: =AVERAGE('Key Ratio'!$I$48,'Key Ratio'!$J$48,'Key Ratio'!$K$48) -> 0.70421678 | C16: =AVERAGE('Key Ratio'!$I$48,'Key Ratio'!$J$48,'Key Ratio'!$K$48) -> 0.70421678 | D16: =AVERAGE('Key Ratio'!$I$48,'Key Ratio'!$J$48,'Key Ratio'!$K$48) -> 0.70421678 | E16: =AVERAGE('Key Ratio'!$I$48,'Key Ratio'!$J$48,'Key Ratio'!$K$48) -> 0.70421678 | F16: =AVERAGE('Key Ratio'!$I$48,'Key Ratio'!$J$48,'Key Ratio'!$K$48) -> 0.70421678
A17: Proporsi Kepentingan Non Pengendali (% Dari Total Ekuitas) | B17: ='Balance Sheet'!$K$75/'Balance Sheet'!$K$77 -> 0.16732882 | C17: ='Balance Sheet'!$K$75/'Balance Sheet'!$K$77 -> 0.16732882 | D17: ='Balance Sheet'!$K$75/'Balance Sheet'!$K$77 -> 0.16732882 | E17: ='Balance Sheet'!$K$75/'Balance Sheet'!$K$77 -> 0.16732882 | F17: ='Balance Sheet'!$K$75/'Balance Sheet'!$K$77 -> 0.16732882
A18: Jumlah Saham Beredar (Miliar Lembar, Diasumsikan Tetap) | B18: ='Income Statement'!$K$42 -> 4.23 | C18: ='Income Statement'!$K$42 -> 4.23 | D18: ='Income Statement'!$K$42 -> 4.23 | E18: ='Income Statement'!$K$42 -> 4.23 | F18: ='Income Statement'!$K$42 -> 4.23
A20: PROYEKSI LAPORAN LABA RUGI
A21: Pendapatan | B21: ='Income Statement'!$K$5*(1+B5) -> 5324.7619 | C21: =B21*(1+C5) -> 7060.1907 | D21: =C21*(1+D5) -> 9361.2245 | E21: =D21*(1+E5) -> 12412.204 | F21: =E21*(1+F5) -> 16457.548
A22: Laba Kotor | B22: =B21*B6 -> 1537.5837 | C22: =C21*C6 -> 2038.7078 | D22: =D21*D6 -> 2703.1567 | E22: =E21*E6 -> 3584.1605 | F22: =F21*F6 -> 4752.2982
A23: Beban Usaha | B23: =-B21*B7 -> -462.98025 | C23: =-C21*C7 -> -613.87324 | D23: =-D21*D7 -> -813.94476 | E23: =-E21*E7 -> -1079.2229 | F23: =-F21*F7 -> -1430.9597
A24: Laba Usaha (EBIT) | B24: =B22+B23 -> 1074.6034 | C24: =C22+C23 -> 1424.8346 | D24: =D22+D23 -> 1889.2119 | E24: =E22+E23 -> 2504.9376 | F24: =F22+F23 -> 3321.3385
A25: Bagian Atas Hasil Bersih Entitas Asosiasi | B25: ='Income Statement'!$K$15*(1+B8) -> 393.84334 | C25: =B25*(1+C8) -> 522.20345 | D25: =C25*(1+D8) -> 692.39826 | E25: =D25*(1+E8) -> 918.0624 | F25: =E25*(1+F8) -> 1217.2743
A26: Beban Keuangan (Bunga) | B26: =-AVERAGE('Key Ratio'!$K$25,B35)*B9 -> -187.85863 | C26: =-AVERAGE(B35,C35)*C9 -> -187.85863 | D26: =-AVERAGE(C35,D35)*D9 -> -187.85863 | E26: =-AVERAGE(D35,E35)*E9 -> -187.85863 | F26: =-AVERAGE(E35,F35)*F9 -> -187.85863
A27: Laba Sebelum Pajak (EBT) | B27: =B24+B25+B26 -> 1280.5881 | C27: =C24+C25+C26 -> 1759.1794 | D27: =D24+D25+D26 -> 2393.7516 | E27: =E24+E25+E26 -> 3235.1414 | F27: =F24+F25+F26 -> 4350.7542
A28: Beban Pajak Penghasilan | B28: =-B27*B10 -> -412.97786 | C28: =-C27*C10 -> -567.31913 | D28: =-D27*D10 -> -771.9628 | E28: =-E27*E10 -> -1043.3033 | F28: =-F27*F10 -> -1403.0781
A29: Laba Bersih Tahun Berjalan | B29: =B27+B28 -> 867.61026 | C29: =C27+C28 -> 1191.8603 | D29: =D27+D28 -> 1621.7888 | E29: =E27+E28 -> 2191.8381 | F29: =F27+F28 -> 2947.6761
A30: Laba Bersih - Pemilik Entitas Induk | B30: =B29*B11 -> 752.25636 | C30: =C29*C11 -> 1033.3954 | D30: =D29*D11 -> 1406.1624 | E30: =E29*E11 -> 1900.4203 | F30: =F29*F11 -> 2555.7652
A31: EPS (Rp) | B31: =B30/B18 -> 177.83838 | C31: =C30/C18 -> 244.30152 | D31: =D30/D18 -> 332.42609 | E31: =E30/E18 -> 449.27194 | F31: =F30/F18 -> 604.1998
A33: PROYEKSI NERACA (SIMPLIFIED)
A34: Total Aset (= Pendapatan / Asset Turnover) | B34: =B21/B16 -> 7561.254 | C34: =C21/C16 -> 10025.593 | D34: =D21/D16 -> 13293.101 | E34: =E21/E16 -> 17625.544 | F34: =F21/F16 -> 23370.002
A35: Total Debt | B35: ='Key Ratio'!$K$25*(1+B15) -> 2547 | C35: =B35*(1+C15) -> 2547 | D35: =C35*(1+D15) -> 2547 | E35: =D35*(1+E15) -> 2547 | F35: =E35*(1+F15) -> 2547
A36: Dividen Dibayar (= Payout% x Laba Bersih Pemilik Tahun Sebelumnya) | B36: ='Income Statement'!$K$30*B12 -> 232.14991 | C36: =B30*C12 -> 388.94487 | D36: =C30*D12 -> 534.30436 | E36: =D30*E12 -> 727.03892 | F36: =E30*F12 -> 982.58889
A37: Ekuitas - Pemilik Entitas Induk | B37: =('Balance Sheet'!$K$77-'Balance Sheet'!$K$75)+B30-B36 -> 4083.1064 | C37: =B37+C30-C36 -> 4727.557 | D37: =C37+D30-D36 -> 5599.415 | E37: =D37+E30-E36 -> 6772.7964 | F37: =E37+F30-F36 -> 8345.9727
A38: Total Ekuitas (Termasuk Kepentingan Non Pengendali) | B38: =B37/(1-B17) -> 4903.624 | C38: =C37/(1-C17) -> 5677.5797 | D38: =D37/(1-D17) -> 6724.6413 | E38: =E37/(1-E17) -> 8133.8186 | F38: =F37/(1-F17) -> 10023.131
A39: Total Liabilitas (Plug = Total Aset - Total Ekuitas) | B39: =B34-B38 -> 2657.6299 | C39: =C34-C38 -> 4348.0131 | D39: =D34-D38 -> 6568.4594 | E39: =E34-E38 -> 9491.7252 | F39: =F34-F38 -> 13346.871
A41: PROYEKSI ARUS KAS (SIMPLIFIED)
A42: Arus Kas Operasi (OCF) | B42: =B21*B14 -> 1081.7863 | C42: =C21*C14 -> 1434.3585 | D42: =D21*D14 -> 1901.8398 | E42: =E21*E14 -> 2521.6811 | F42: =F21*F14 -> 3343.539
A43: Belanja Modal (Capex) | B43: =-B21*B13 -> -680.35473 | C43: =-C21*C13 -> -902.09368 | D43: =-D21*D13 -> -1196.1011 | E43: =-E21*E13 -> -1585.9303 | F43: =-F21*F13 -> -2102.8115
A44: Free Cash Flow (FCF) | B44: =B42+B43 -> 401.43154 | C44: =C42+C43 -> 532.26477 | D44: =D42+D43 -> 705.73873 | E44: =E42+E43 -> 935.75075 | F44: =F42+F43 -> 1240.7275
A45: Free Cash Flow Per Share (Rp) | B45: =B44/B18 -> 94.901072 | C45: =C44/C18 -> 125.83091 | D45: =D44/D18 -> 166.84131 | E45: =E44/E18 -> 221.21767 | F45: =F44/F18 -> 293.3162
A46: Kas Dan Setara Kas Akhir Periode | B46: ='Balance Sheet'!$K$10+B42+B43+(B35-'Key Ratio'!$K$25)-B36 -> 1688.2816 | C46: =B46+C42+C43+(C35-B35)-C36 -> 1831.6015 | D46: =C46+D42+D43+(D35-C35)-D36 -> 2003.0359 | E46: =D46+E42+E43+(E35-D35)-E36 -> 2211.7477 | F46: =E46+F42+F43+(F35-E35)-F36 -> 2469.8864
A47: Net Debt | B47: =B35-B46 -> 858.71838 | C47: =C35-C46 -> 715.39849 | D47: =D35-D46 -> 543.96411 | E47: =E35-E46 -> 335.25228 | F47: =F35-F46 -> 77.113643
A49: PROYEKSI KEY RATIO
A50: Return on Assets - ROA (%) | B50: =B30/B34 -> 0.099488307 | C50: =C30/C34 -> 0.10307574 | D50: =D30/D34 -> 0.10578137 | E50: =E30/E34 -> 0.10782194 | F50: =F30/F34 -> 0.10936093
A51: Return on Equity - ROE (%) | B51: =B30/B37 -> 0.18423628 | C51: =C30/C37 -> 0.21858973 | D51: =D30/D37 -> 0.25112666 | E51: =E30/E37 -> 0.28059611 | F51: =F30/F37 -> 0.30622736
A52: Debt to Equity Ratio (x) | B52: =B35/B37 -> 0.62378976 | C52: =C35/C37 -> 0.53875606 | D52: =D35/D37 -> 0.45486894 | E52: =E35/E37 -> 0.37606328 | F52: =F35/F37 -> 0.30517713
A53: Financial Leverage (x) | B53: =B34/B37 -> 1.8518386 | C53: =C34/C37 -> 2.1206709 | D53: =D34/D37 -> 2.374016 | E53: =E34/E37 -> 2.6024027 | F53: =F34/F37 -> 2.8001532
A54: Net Debt/Total Equity (x) | B54: =B47/B37 -> 0.21031006 | C54: =C47/C37 -> 0.1513252 | D54: =D47/D37 -> 0.097146597 | E54: =E47/E37 -> 0.049499831 | F54: =F47/F37 -> 0.0092396233
A55: Book Value Per Share (Rp) | B55: =B37/B18 -> 965.27339 | C55: =C37/C18 -> 1117.6258 | D55: =D37/D18 -> 1323.7388 | E55: =E37/E18 -> 1601.1339 | F55: =F37/F18 -> 1973.0432
A60: DATA PENDUKUNG 12M 2026F (Q1 Aktual + Forecast Q2-Q4) -- dalam Miliar Rupiah
A61: Pendapatan Q1 2026 Aktual (Miliar Rp) | B61: 932
A62: Pendapatan Q1 2025 Aktual (Miliar Rp) | B62: 1081
A63: Pendapatan FY2025 Aktual (Miliar Rp) | B63: ='Income Statement'!$K$5 -> 4394
A64: Pendapatan Q2-Q4 2025 Aktual (Miliar Rp) | B64: =B63-B62 -> 3313
A65: Growth Rate Top-Down (CAGR 3-Tahun Historis, %) | B65: =('Income Statement'!$K$5/'Income Statement'!$H$5)^(1/3)-1 -> 0.32591668
A66: Pendapatan Q2-Q4 2026F (Miliar Rp) | B66: =B64*(1+B65) -> 4392.7619
A67: Pendapatan FY2026F (Miliar Rp) = Q1 Aktual + Q2-Q4F | B67: =B61+B66 -> 5324.7619
A68: Growth Rate FY2026F vs FY2025 (%) -- INI YANG DIPAKAI DI B5 | B68: =B67/B63-1 -> 0.21182566

Sheet Income Statement
A1: INCOME STATEMENT - PT Rukun Raharja Tbk (RAJA)
A4: Keterangan | B4: 12M 2016 | C4: 12M 2017 | D4: 12M 2018 | E4: 12M 2019 | F4: 12M 2020 | G4: 12M 2021 | H4: 12M 2022 | I4: 12M 2023 | J4: 12M 2024 | K4: 12M 2025
A5: Total Pendapatan | B5: 2487 | C5: 1993 | D5: 1683 | E5: 1728 | F5: 1440 | G5: 1405 | H5: 1885 | I5: 3108 | J5: 4033 | K5: 4394
A6: Total Beban Pokok Penjualan | B6: -2165 | C6: -1665 | D6: -1391 | E6: -1486 | F6: -1205 | G6: -1184 | H6: -1512 | I6: -2102 | J6: -2936 | K6: -3205
A7: Laba Kotor | B7: =B5+B6 -> 322 | C7: =C5+C6 -> 328 | D7: =D5+D6 -> 292 | E7: =E5+E6 -> 242 | F7: =F5+F6 -> 235 | G7: =G5+G6 -> 221 | H7: =H5+H6 -> 373 | I7: =I5+I6 -> 1006 | ... K7: =K5+K6 -> 1189
A8: Total Beban Usaha | B8: -168 | C8: -302 | D8: -204 | E8: -202 | F8: -152 | G8: -155 | H8: -189 | I8: -273 | J8: -315 | K8: -417
A9: Laba Usaha (Operating Profit) | B9: =B7+B8 -> 154 | C9: =C7+C8 -> 26 | D9: =D7+D8 -> 88 | E9: =E7+E8 -> 40 | F9: =F7+F8 -> 83 | G9: =G7+G8 -> 66 | H9: =H7+H8 -> 184 | I9: =I7+I8 -> 733 | ... K9: =K7+K8 -> 772
A11: Penghasilan/(Beban) Lain-Lain
A12: Laba (Rugi) Selisih Kurs | B12: -2 | C12: 0 | D12: 0 | E12: 15 | F12: -7 | G12: 1 | H12: -31 | I12: 5 | J12: -5 | K12: -37
A13: Pendapatan Keuangan | B13: 0 | C13: 0 | D13: 0 | E13: 0 | F13: 0 | G13: 0 | H13: 0 | I13: 0 | J13: 0 | K13: 0
A14: Beban Keuangan | B14: -52 | C14: -74 | D14: -94 | E14: -47 | F14: -44 | G14: -35 | H14: -40 | I14: -141 | J14: -164 | K14: -166
A15: Bagian Atas Hasil Bersih Entitas Asosiasi | B15: 0 | C15: 0 | D15: 0 | E15: 0 | F15: 0 | G15: 44 | H15: 104 | I15: 114 | J15: 98 | K15: 325
A16: Laba (Rugi) Atas Penjualan Aset Tetap | B16: 0 | C16: 301 | D16: 0 | E16: 0 | F16: 0 | G16: 0 | H16: 0 | I16: 0 | J16: 0 | K16: 0
A17: Adjustment | B17: 0 | C17: 0 | D17: 0 | E17: 0 | F17: 0 | G17: 0 | H17: 0 | I17: 0 | J17: 0 | K17: 0
A18: Others | B18: 44 | C18: -8 | D18: 220 | E18: 120 | F18: 34 | G18: -9 | H18: -22 | I18: -90 | J18: -11 | K18: -78
A19: Total Penghasilan/(Beban) Lain-Lain | B19: =SUM(B12:B18) -> -10 | C19: =SUM(C12:C18) -> 219 | D19: =SUM(D12:D18) -> 126 | E19: =SUM(E12:E18) -> 88 | F19: =SUM(F12:F18) -> -17 | G19: =SUM(G12:G18) -> 1 | H19: =SUM(H12:H18) -> 11 | I19: =SUM(I12:I18) -> -112 | ... K19: =SUM(K12:K18) -> 44
A20: Laba Sebelum Pajak | B20: =B9+B19 -> 144 | C20: =C9+C19 -> 245 | D20: =D9+D19 -> 214 | E20: =E9+E19 -> 128 | F20: =F9+F19 -> 66 | G20: =G9+G19 -> 67 | H20: =H9+H19 -> 195 | I20: =I9+I19 -> 621 | ... K20: =K9+K19 -> 816
A21: Beban Pajak Penghasilan | B21: -42 | C21: -60 | D21: -38 | E21: -38 | F21: -29 | G21: -18 | H21: -32 | I21: -206 | J21: -240 | K21: -239
A22: Laba Bersih Dari Operasi Yang Dilanjutkan | B22: 103 | C22: 185 | D22: 177 | E22: 90 | F22: 37 | G22: 49 | H22: 161 | I22: 414 | J22: 461 | K22: 577
A23: Hak Minoritas | B23: 0 | C23: 0 | D23: 0 | E23: 0 | F23: 0 | G23: 0 | H23: 0 | I23: 0 | J23: 0 | K23: 0
A24: Laba Pra Akuisisi | B24: 0 | C24: 0 | D24: 0 | E24: 0 | F24: 0 | G24: 0 | H24: 0 | I24: 0 | J24: 0 | K24: 0
A25: Laba Bersih Tahun Berjalan | B25: =B22+B24 -> 103 | C25: =C22+C24 -> 185 | D25: =D22+D24 -> 177 | E25: =E22+E24 -> 90 | F25: =F22+F24 -> 37 | G25: =G22+G24 -> 49 | H25: =H22+H24 -> 161 | I25: =I22+I24 -> 414 | ... K25: =K22+K24 -> 577
A26: Pendapatan Komprehensif Lain | B26: 3 | C26: 8 | D26: 2 | E26: -2 | F26: -1 | G26: 2 | H26: 0 | I26: -2 | J26: 0 | K26: -23
A27: Jumlah Laba Komprehensif | B27: =B25+B26 -> 106 | C27: =C25+C26 -> 193 | D27: =D25+D26 -> 179 | E27: =E25+E26 -> 88 | F27: =F25+F26 -> 36 | G27: =G25+G26 -> 51 | H27: =H25+H26 -> 161 | I27: =I25+I26 -> 412 | ... K27: =K25+K26 -> 554
A29: Laba Bersih Yang Dapat Diatribusikan Kepada:
A30: Pemilik Entitas Induk | B30: 87 | C30: 156 | D30: 163 | E30: 81 | F30: 20 | G30: 32 | H30: 131 | I30: 391 | J30: 405 | K30: 449
A31: Kepentingan Non-Pengendali | B31: 16 | C31: 29 | D31: 14 | E31: 9 | F31: 17 | G31: 16 | H31: 30 | I31: 24 | J31: 56 | K31: 128
A32: Laba Pra Akuisisi | B32: - | C32: - | D32: - | E32: - | F32: - | G32: - | H32: - | I32: - | J32: - | K32: -
A33: Total Laba Bersih Yang Dapat Diatribusikan | B33: =SUM(B30:B32) -> 103 | C33: =SUM(C30:C32) -> 185 | D33: =SUM(D30:D32) -> 177 | E33: =SUM(E30:E32) -> 90 | F33: =SUM(F30:F32) -> 37 | G33: =SUM(G30:G32) -> 48 | H33: =SUM(H30:H32) -> 161 | I33: =SUM(I30:I32) -> 415 | ... K33: =SUM(K30:K32) -> 577
A35: Laba Komprehensif Yang Dapat Diatribusikan Kepada:
A36: Pemilik Entitas Induk | B36: 89 | C36: 161 | D36: 165 | E36: 79 | F36: 19 | G36: 34 | H36: 132 | I36: 389 | J36: 405 | K36: 427
A37: Kepentingan Non-Pengendali | B37: 17 | C37: 31 | D37: 15 | E37: 9 | F37: 16 | G37: 17 | H37: 30 | I37: 23 | J37: 56 | K37: 127
A38: Total Laba Komprehensif Yang Dapat Diatribusikan | B38: =SUM(B36:B37) -> 106 | C38: =SUM(C36:C37) -> 192 | D38: =SUM(D36:D37) -> 180 | E38: =SUM(E36:E37) -> 88 | F38: =SUM(F36:F37) -> 35 | G38: =SUM(G36:G37) -> 51 | H38: =SUM(H36:H37) -> 162 | I38: =SUM(I36:I37) -> 412 | ... K38: =SUM(K36:K37) -> 554
A41: Key Ratio
A42: Share Outstanding | B42: 4.08 | C42: 4.08 | D42: 4.23 | E42: 4.23 | F42: 4.23 | G42: 4.23 | H42: 4.23 | I42: 4.23 | J42: 4.23 | K42: 4.23
A43: EPS (Annual) | B43: =B30/B42 -> 21.323529 | C43: =C30/C42 -> 38.235294 | D43: =D30/D42 -> 38.534279 | E43: =E30/E42 -> 19.148936 | F43: =F30/F42 -> 4.7281324 | G43: =G30/G42 -> 7.5650118 | H43: =H30/H42 -> 30.969267 | I43: =I30/I42 -> 92.434988 | ... K43: =K30/K42 -> 106.14657

Sheet Balance Sheet
A1: BALANCE SHEET - PT Rukun Raharja Tbk (RAJA)
A4: Keterangan | B4: 12M 2016 | C4: 12M 2017 | D4: 12M 2018 | E4: 12M 2019 | F4: 12M 2020 | G4: 12M 2021 | H4: 12M 2022 | I4: 12M 2023 | J4: 12M 2024 | K4: 12M 2025
A5: ASET
A6: Aset Lancar
A7: Kas Dan Setara Kas
A8: Kas Dan Setara Kas | B8: 174 | C8: 174 | D8: 290 | E8: 304 | F8: 547 | G8: 555 | H8: 469 | I8: 538 | J8: 717 | K8: 1519
A9: Pihak Ketiga | B9: 0 | C9: 0 | D9: 0 | E9: 0 | F9: 0 | G9: 0 | H9: 0 | I9: 0 | J9: 4 | K9: 0
A10: Total Kas Dan Setara Kas | B10: 174 | C10: 174 | D10: 290 | E10: 304 | F10: 547 | G10: 555 | H10: 469 | I10: 538 | J10: 717 | K10: 1519
A11: Piutang Usaha
A12: Pihak Berelasi | B12: 6 | C12: 5 | D12: 7 | E12: 1 | F12: 0 | G12: 0 | H12: 0 | I12: 0 | J12: 0 | K12: 83
A13: Pihak Ketiga | B13: 119 | C13: 258 | D13: 200 | E13: 213 | F13: 150 | G13: 175 | H13: 255 | I13: 471 | J13: 542 | K13: 469
A14: Total Piutang Usaha | B14: 125 | C14: 262 | D14: 207 | E14: 214 | F14: 150 | G14: 175 | H14: 255 | I14: 471 | J14: 542 | K14: 551
A15: Piutang Lain-Lain
A16: Pihak Berelasi | B16: 8 | C16: 7 | D16: 282 | E16: 258 | F16: 22 | G16: 6 | H16: 5 | I16: 94 | J16: 68 | K16: 3
A17: Pihak Ketiga | B17: 41 | C17: 80 | D17: 78 | E17: 108 | F17: 72 | G17: 77 | H17: 64 | I17: 59 | J17: 43 | K17: 95
A18: Total Piutang Lain-Lain | B18: 49 | C18: 88 | D18: 360 | E18: 367 | F18: 94 | G18: 82 | H18: 69 | I18: 153 | J18: 111 | K18: 97
A19: Persediaan | B19: 52 | C19: 99 | D19: 2 | E19: 2 | F19: 4 | G19: 7 | H19: 12 | I19: 11 | J19: 9 | K19: 11
A20: Investasi Jangka Pendek | B20: 0 | C20: 0 | D20: 0 | E20: 0 | F20: 0 | G20: 0 | H20: 0 | I20: 0 | J20: 0 | K20: 10
A21: Aset Lancar Lainnya (Others) | B21: 40 | C21: 47 | D21: 109 | E21: 98 | F21: 71 | G21: 133 | H21: 109 | I21: 69 | J21: 88 | K21: 112
A22: TOTAL ASET LANCAR | B22: 440 | C22: 671 | D22: 968 | E22: 984 | F22: 868 | G22: 953 | H22: 914 | I22: 1243 | J22: 1467 | K22: 2301
A24: TOTAL ASET TIDAK LANCAR | B24: 1511 | C24: 1368 | D24: 1799 | E24: 1524 | F24: 1483 | G24: 2554 | H24: 3148 | I24: 3831 | J24: 3886 | K24: 5685
A26: TOTAL ASET | B26: 1951 | C26: 2039 | D26: 2767 | E26: 2508 | F26: 2351 | G26: 3506 | H26: 4062 | I26: 5074 | J26: 5354 | K26: 7986
A28: LIABILITAS DAN EKUITAS
A29: Liabilitas
A30: Liabilitas Jangka Pendek
A31: Utang Bank Jangka Pendek | B31: 0 | C31: 0 | D31: 0 | E31: 0 | F31: 0 | G31: 15 | H31: 0 | I31: 30 | J31: 27 | K31: 125
A32: Utang Usaha
A33: Pihak Ketiga | B33: 65 | C33: 123 | D33: 114 | E33: 125 | F33: 105 | G33: 109 | H33: 168 | I33: 295 | J33: 299 | K33: 440
A34: Pihak Berelasi | B34: 0 | C34: 0 | D34: 0 | E34: 0 | F34: 0 | G34: 0 | H34: 0 | I34: 0 | J34: 0 | K34: 0
A35: Total Utang Usaha | B35: 65 | C35: 123 | D35: 114 | E35: 125 | F35: 105 | G35: 109 | H35: 168 | I35: 295 | J35: 299 | K35: 440
A36: Utang Pajak | B36: 12 | C36: 34 | D36: 38 | E36: 17 | F36: 24 | G36: 22 | H36: 31 | I36: 62 | J36: 79 | K36: 78
A37: Utang Lain-Lain
A38: Pihak Berelasi | B38: 0 | C38: 0 | D38: 0 | E38: 0 | F38: 0 | G38: 2 | H38: 0 | I38: 8 | J38: 9 | K38: 1
A39: Pihak Ketiga | B39: 7 | C39: 3 | D39: 4 | E39: 11 | F39: 15 | G39: 12 | H39: 8 | I39: 19 | J39: 8 | K39: 11
A40: Total Utang Lain-Lain | B40: 7 | C40: 3 | D40: 4 | E40: 11 | F40: 15 | G40: 14 | H40: 8 | I40: 27 | J40: 17 | K40: 13
A41: Beban Akrual | B41: 3 | C41: 3 | D41: 2 | E41: 2 | F41: 3 | G41: 6 | H41: 12 | I41: 36 | J41: 80 | K41: 144
A42: Utang Surat Promes | B42: 0 | C42: 0 | D42: 0 | E42: 0 | F42: 0 | G42: 0 | H42: 0 | I42: 0 | J42: 0 | K42: 0
A43: Bagian Lancar Atas Liabilitas Jangka Panjang
A44: Utang Bank Jangka Panjang | B44: 207 | C44: 102 | D44: 94 | E44: 167 | F44: 155 | G44: 110 | H44: 183 | I44: 400 | J44: 350 | K44: 582
A45: Utang Pembelian Aset | B45: 0 | C45: 0 | D45: 0 | E45: 0 | F45: 0 | G45: 0 | H45: 5 | I45: 2 | J45: 2 | K45: 0
A46: Utang Sewa Pembiayaan | B46: 1 | C46: 2 | D46: 3 | E46: 1 | F46: 1 | G46: 1 | H46: 3 | I46: 7 | J46: 11 | K46: 15
A47: Others | B47: 0 | C47: 0 | D47: 0 | E47: 0 | F47: 0 | G47: 1 | H47: 5 | I47: 3 | J47: 9 | K47: 10
A48: Total Bagian Lancar Atas Liabilitas Jangka Panjang | B48: 208 | C48: 104 | D48: 97 | E48: 168 | F48: 156 | G48: 111 | H48: 196 | I48: 412 | J48: 372 | K48: 607
A49: Liabilitas Jangka Pendek Lainnya (Others) | B49: 9 | C49: 26 | D49: 4 | E49: 5 | F49: 6 | G49: 5 | H49: 6 | I49: 8 | J49: 70 | K49: 187
A50: TOTAL LIABILITAS JANGKA PENDEK | B50: 303 | C50: 294 | D50: 258 | E50: 327 | F50: 308 | G50: 281 | H50: 421 | I50: 870 | J50: 944 | K50: 1594
A52: Liabilitas Jangka Panjang
A53: Liabilitas Pajak Tangguhan | B53: 0 | C53: 0 | D53: 0 | E53: 0 | F53: 0 | G53: 0 | H53: 0 | I53: 0 | J53: 0 | K53: 0
A54: Utang Bank & Sewa Pembiayaan Jangka Panjang
A55: Utang Bank Jangka Panjang | B55: 395 | C55: 93 | D55: 579 | E55: 452 | F55: 278 | G55: 1409 | H55: 1526 | I55: 1648 | J55: 1437 | K55: 1809
A56: Utang Pembelian Aset | B56: 0 | C56: 0 | D56: 0 | E56: 0 | F56: 0 | G56: 0 | H56: 8 | I56: 0 | J56: 1 | K56: 0
A57: Utang Sewa Pembiayaan | B57: 1 | C57: 3 | D57: 3 | E57: 2 | F57: 5 | G57: 2 | H57: 8 | I57: 13 | J57: 20 | K57: 16
A58: Others | B58: 0 | C58: 0 | D58: 0 | E58: 0 | F58: 0 | G58: 5 | H58: 5 | I58: 4 | J58: 6 | K58: 10
A59: Total Utang Bank & Sewa Pembiayaan Jangka Panjang | B59: 396 | C59: 96 | D59: 582 | E59: 454 | F59: 283 | G59: 1416 | H59: 1546 | I59: 1664 | J59: 1464 | K59: 1835
A60: Utang Obligasi | B60: 0 | C60: 0 | D60: 0 | E60: 0 | F60: 0 | G60: 0 | H60: 0 | I60: 0 | J60: 0 | K60: 0
A61: Utang Jangka Panjang Lainnya | B61: 0 | C61: 0 | D61: 0 | E61: 0 | F61: 0 | G61: 0 | H61: 0 | I61: 0 | J61: 0 | K61: 0
A62: Liabilitas Jangka Panjang Lainnya (Others) | B62: 23 | C62: 21 | D62: 19 | E62: 22 | F62: 22 | G62: 23 | H62: 20 | I62: 154 | J62: 169 | K62: 278
A63: TOTAL LIABILITAS JANGKA PANJANG | B63: 419 | C63: 117 | D63: 601 | E63: 476 | F63: 305 | G63: 1439 | H63: 1566 | I63: 1818 | J63: 1633 | K63: 2113
A65: TOTAL LIABILITAS | B65: 722 | C65: 410 | D65: 859 | E65: 803 | F65: 612 | G65: 1720 | H65: 1987 | I65: 2688 | J65: 2577 | K65: 3707
A67: Ekuitas
A68: Modal Saham | B68: 142 | C68: 143 | D68: 159 | E68: 152 | F68: 155 | G68: 157 | H68: 171 | I68: 169 | J68: 177 | K68: 183
A69: Tambahan Modal Disetor | B69: 286 | C69: 288 | D69: 336 | E69: 323 | F69: 327 | G69: 331 | H69: 362 | I69: 359 | J69: 375 | K69: 538
A70: Saldo Laba
A71: Telah Ditentukan Penggunaannya | B71: 0 | C71: 0 | D71: 0 | E71: 0 | F71: 0 | G71: 0 | H71: 0 | I71: 0 | J71: 1 | K71: 3
A72: Belum Ditentukan Penggunaannya | B72: 412 | C72: 557 | D72: 740 | E72: 842 | F72: 852 | G72: 886 | H72: 1074 | I72: 1388 | J72: 1703 | K72: 1854
A73: Total Saldo Laba | B73: 412 | C73: 557 | D73: 740 | E73: 842 | F73: 852 | G73: 886 | H73: 1075 | I73: 1388 | J73: 1704 | K73: 1858
A74: Adjustment | B74: 0 | C74: 0 | D74: 0 | E74: 0 | F74: 0 | G74: 0 | H74: 0 | I74: 0 | J74: 0 | K74: 0
A75: Kepentingan Non Pengendali | B75: 303 | C75: 554 | D75: 579 | E75: 299 | F75: 315 | G75: 333 | H75: 381 | I75: 385 | J75: 432 | K75: 716
A76: Ekuitas Lainnya (Others) | B76: 87 | C76: 86 | D76: 94 | E76: 89 | F76: 90 | G76: 79 | H76: 86 | I76: 85 | J76: 89 | K76: 985
A77: TOTAL EKUITAS | B77: 1229 | C77: 1629 | D77: 1908 | E77: 1706 | F77: 1738 | G77: 1786 | H77: 2075 | I77: 2386 | J77: 2777 | K77: 4279
A79: TOTAL LIABILITAS DAN EKUITAS | B79: 1951 | C79: 2039 | D79: 2767 | E79: 2508 | F79: 2351 | G79: 3506 | H79: 4062 | I79: 5074 | J79: 5354 | K79: 7986
A81: Saham Beredar (Miliar Lembar) | B81: 4 | C81: 4 | D81: 4 | E81: 4 | F81: 4 | G81: 4 | H81: 4 | I81: 4 | J81: 4 | K81: 4
A83: Cek Keseimbangan (Total Aset - Total Liabilitas & Ekuitas) | B83: =B26-B79 -> 0 | C83: =C26-C79 -> 0 | D83: =D26-D79 -> 0 | E83: =E26-E79 -> 0 | F83: =F26-F79 -> 0 | G83: =G26-G79 -> 0 | H83: =H26-H79 -> 0 | I83: =I26-I79 -> 0 | ... K83: =K26-K79 -> 0

Sheet Cash Flow
A1: CASH FLOW - PT Rukun Raharja Tbk (RAJA)
A4: Keterangan | B4: 12M 2025 | C4: 12M 2024 | D4: 12M 2023 | E4: 12M 2022 | F4: 12M 2021 | G4: 12M 2020 | H4: 12M 2019 | I4: 12M 2018 | J4: 12M 2017 | K4: 12M 2016
A5: ARUS KAS DARI AKTIVITAS OPERASI
A6: Penerimaan Kas Dari Pelanggan | B6: 4480 | C6: 4128 | D6: 2916 | E6: 1913 | F6: 1385 | G6: 1461 | H6: 1684 | I6: 1849 | J6: 1899 | K6: 2528
A7: Penerimaan Dari Pemegang Saham | B7: 0 | C7: 0 | D7: 0 | E7: 0 | F7: 0 | G7: 0 | H7: 0 | I7: 0 | J7: 0 | K7: 0
A8: Penerimaan Dari Anak Perusahaan | B8: 0 | C8: 0 | D8: 0 | E8: 0 | F8: 0 | G8: 0 | H8: 0 | I8: 0 | J8: 0 | K8: 0
A9: Pembayaran Kas Kepada Pemasok Dan Karyawan
A10: Pemasok Dan Lain-Lain | B10: 0 | C10: 0 | D10: 0 | E10: 0 | F10: 0 | G10: 0 | H10: 0 | I10: 0 | J10: 0 | K10: 0
A11: Karyawan | B11: 0 | C11: 0 | D11: 0 | E11: 0 | F11: 0 | G11: 0 | H11: 0 | I11: 0 | J11: 0 | K11: 0
A12: Total Pembayaran Kas Kepada Pemasok Dan Karyawan | B12: -3104 | C12: -3041 | D12: -1957 | E12: -1567 | F12: -1207 | G12: -1173 | H12: -1547 | I12: -1536 | J12: -1916 | K12: -2286
A13: Penerimaan Bunga | B13: 0 | C13: 0 | D13: 0 | E13: 0 | F13: 0 | G13: 0 | H13: 0 | I13: 0 | J13: 0 | K13: 0
A14: Pembayaran Bunga Dan Beban Keuangan | B14: -153 | C14: -153 | D14: -126 | E14: -101 | F14: -75 | G14: -31 | H14: -29 | I14: -80 | J14: -34 | K14: -39
A15: Pembayaran Pajak Penghasilan | B15: -258 | C15: -201 | D15: -182 | E15: -42 | F15: -38 | G15: -23 | H15: -69 | I15: -75 | J15: -64 | K15: -49
A16: Penerimaan Restitusi Pajak | B16: 1 | C16: 4 | D16: 5 | E16: 9 | F16: 13 | G16: 0 | H16: 0 | I16: 0 | J16: 0 | K16: 0
A17: Penerimaan (Pembayaran) Dana Lain-Lain | B17: -83 | C17: 36 | D17: 18 | E17: -28 | F17: -129 | G17: 7 | H17: 27 | I17: -4 | J17: 0 | K17: -3
A18: Total Arus Kas Dari Aktivitas Operasi | B18: =B6+B7+B8+B12+B13+B14+B15+B16+B17 -> 883 | C18: =C6+C7+C8+C12+C13+C14+C15+C16+C17 -> 773 | D18: =D6+D7+D8+D12+D13+D14+D15+D16+D17 -> 674 | E18: =E6+E7+E8+E12+E13+E14+E15+E16+E17 -> 184 | F18: =F6+F7+F8+F12+F13+F14+F15+F16+F17 -> -51 | G18: =G6+G7+G8+G12+G13+G14+G15+G16+G17 -> 241 | H18: =H6+H7+H8+H12+H13+H14+H15+H16+H17 -> 66 | I18: =I6+I7+I8+I12+I13+I14+I15+I16+I17 -> 154 | ... K18: =K6+K7+K8+K12+K13+K14+K15+K16+K17 -> 151
A20: ARUS KAS DARI AKTIVITAS INVESTASI
A21: Perolehan Aset Tetap | B21: -745 | C21: -164 | D21: -538 | E21: -335 | F21: -995 | G21: -28 | H21: -137 | I21: -13 | J21: -11 | K21: -154
A22: Pelepasan Aset Tetap | B22: 7 | C22: 1 | D22: 9 | E22: 1 | F22: 1 | G22: 0 | H22: 1 | I22: 1 | J22: 0 | K22: 1
A23: Perolehan Aset Tak Berwujud | B23: -1 | C23: -1 | D23: -1 | E23: -7 | F23: -1 | G23: 0 | H23: 0 | I23: 0 | J23: 0 | K23: 0
A24: Perolehan Properti Pertambangan | B24: -22 | C24: -16 | D24: -409 | E24: 0 | F24: 0 | G24: 0 | H24: 0 | I24: 0 | J24: 0 | K24: 0
A25: Pembayaran Uang Muka Proyek | B25: 0 | C25: 0 | D25: 0 | E25: 0 | F25: 0 | G25: 0 | H25: 0 | I25: 0 | J25: 0 | K25: 0
A26: Penurunan (Kenaikan) Uang Muka Investasi | B26: 0 | C26: 0 | D26: 0 | E26: 0 | F26: 0 | G26: -9 | H26: -179 | I26: -33 | J26: 513 | K26: -1
A27: Pengeluaran Kas Untuk Akuisisi | B27: -399 | C27: -43 | D27: 0 | E27: 0 | F27: 0 | G27: 0 | H27: 0 | I27: 0 | J27: 0 | K27: 0
A28: Pelepasan Entitas Anak | B28: 0 | C28: 0 | D28: 0 | E28: 0 | F28: 0 | G28: 0 | H28: 0 | I28: 0 | J28: 0 | K28: 0
A29: Laba Atas Penjualan Aset Tetap | B29: 0 | C29: 0 | D29: 0 | E29: 0 | F29: 0 | G29: 0 | H29: 0 | I29: 0 | J29: 0 | K29: 0
A30: Penerimaan Dividen | B30: 106 | C30: 120 | D30: 147 | E30: 114 | F30: 34 | G30: 0 | H30: 0 | I30: 0 | J30: 0 | K30: 0
A31: Penempatan Investasi Jangka Panjang (1) | B31: -10 | C31: 0 | D31: 0 | E31: 0 | F31: 0 | G31: 0 | H31: 0 | I31: 0 | J31: 0 | K31: 0
A32: Penempatan Investasi Jangka Panjang (2) | B32: -202 | C32: 0 | D32: 0 | E32: 0 | F32: 0 | G32: 0 | H32: 0 | I32: 0 | J32: 0 | K32: 0
... A42: Pelepasan (Penambahan) Aset Lainnya | B42: 0 | C42: 0 | D42: 0 | E42: 5 | F42: -2 | G42: -12 | H42: -20 | I42: -35 | J42: 50 | K42: -58
A43: Total Arus Kas Dari Aktivitas Investasi | B43: =B21+B22+B23+B24+B25+B26+B27+B28+B29+B30+B31+B32+B33+B34+B35+B36+B37+B38+B39+B40+B41+B42 -> -695 | C43: =C21+C22+C23+C24+C25+C26+C27+C28+C29+C30+C31+C32+C33+C34+C35+C36+C37+C38+C39+C40+C41+C42 -> -56 | D43: =D21+D22+D23+D24+D25+D26+D27+D28+D29+D30+D31+D32+D33+D34+D35+D36+D37+D38+D39+D40+D41+D42 -> -824 | E43: =E21+E22+E23+E24+E25+E26+E27+E28+E29+E30+E31+E32+E33+E34+E35+E36+E37+E38+E39+E40+E41+E42 -> -225 | F43: =F21+F22+F23+F24+F25+F26+F27+F28+F29+F30+F31+F32+F33+F34+F35+F36+F37+F38+F39+F40+F41+F42 -> -1035 | G43: =G21+G22+G23+G24+G25+G26+G27+G28+G29+G30+G31+G32+G33+G34+G35+G36+G37+G38+G39+G40+G41+G42 -> -49 | H43: =H21+H22+H23+H24+H25+H26+H27+H28+H29+H30+H31+H32+H33+H34+H35+H36+H37+H38+H39+H40+H41+H42 -> -335 | I43: =I21+I22+I23+I24+I25+I26+I27+I28+I29+I30+I31+I32+I33+I34+I35+I36+I37+I38+I39+I40+I41+I42 -> -80 | ... K43: =K21+K22+K23+K24+K25+K26+K27+K28+K29+K30+K31+K32+K33+K34+K35+K36+K37+K38+K39+K40+K41+K42 -> -212
A45: ARUS KAS DARI AKTIVITAS PENDANAAN
A46: (Penambahan) Pencairan Kas Yang Dibatasi | B46: 0 | C46: 0 | D46: 0 | E46: 0 | F46: 0 | G46: 0 | H46: 0 | I46: 0 | J46: 0 | K46: 0
A47: Penerimaan Dari (Pembayaran Kepada) Pihak Berelasi | B47: 0 | C47: 0 | D47: 0 | E47: 0 | F47: 0 | G47: 0 | H47: 0 | I47: 0 | J47: 0 | K47: 0
A48: Penerimaan Deviden | B48: 0 | C48: 0 | D48: 0 | E48: 0 | F48: 0 | G48: 21 | H48: 19 | I48: 0 | J48: 0 | K48: 0
A49: Pembayaran Deviden | B49: -251 | C49: -162 | D49: -69 | E49: -31 | F49: -28 | G49: -27 | H49: -33 | I49: -47 | J49: -13 | K49: -7
A50: Pembayaran Dividen Kas Entitas Anak Ke Non Pengendali | B50: -59 | C50: -20 | D50: -16 | E50: -13 | F50: 0 | G50: 0 | H50: 0 | I50: 0 | J50: 0 | K50: 0
A51: Penerimaan Kas Dari Penambahan Modal Non Pengendali | B51: 0 | C51: 0 | D51: 0 | E51: 0 | F51: 0 | G51: 0 | H51: 0 | I51: 34 | J51: 0 | K51: 0
A52: Pembelian Saham Treasuri | B52: 0 | C52: 0 | D52: 0 | E52: 0 | F52: 0 | G52: 0 | H52: 0 | I52: 0 | J52: 0 | K52: 0
A53: Penambahan Modal Hasil Penawaran Umum | B53: 0 | C53: 0 | D53: 0 | E53: 0 | F53: 0 | G53: 0 | H53: 0 | I53: 0 | J53: 0 | K53: 0
A54: Penerimaan (Pembayaran) Utang Pihak Berelasi | B54: 0 | C54: 0 | D54: 0 | E54: 0 | F54: 0 | G54: 0 | H54: 0 | I54: 0 | J54: 0 | K54: 0
A55: Penambahan (Pengurangan) Utang Jangka Pendek Lainnya | B55: 54 | C55: 29 | D55: -77 | E55: 0 | F55: 14 | G55: 241 | H55: 326 | I55: -696 | J55: 1 | K55: 9
A56: Penerimaan Dari Penerbitan Obligasi/Surat Utang | B56: 0 | C56: 0 | D56: 0 | E56: 0 | F56: 0 | G56: 0 | H56: 0 | I56: 0 | J56: 0 | K56: 0
A57: Pembayaran Biaya Emisi Dan Penerbitan Saham | B57: 0 | C57: 0 | D57: 0 | E57: 0 | F57: 0 | G57: 0 | H57: 0 | I57: 0 | J57: 0 | K57: 0
... A71: Adjustment | B71: 0 | C71: 0 | D71: 0 | E71: 0 | F71: 0 | G71: 0 | H71: 0 | I71: 0 | J71: 0 | K71: 0
A72: Total Arus Kas Dari Aktivitas Pendanaan | B72: =B46+B47+B48+B49+B50+B51+B52+B53+B54+B55+B56+B57+B58+B59+B60+B61+B62+B63+B64+B65+B66+B67+B68+B69+B70+B71 -> 666 | C72: =C46+C47+C48+C49+C50+C51+C52+C53+C54+C55+C56+C57+C58+C59+C60+C61+C62+C63+C64+C65+C66+C67+C68+C69+C70+C71 -> -558 | D72: =D46+D47+D48+D49+D50+D51+D52+D53+D54+D55+D56+D57+D58+D59+D60+D61+D62+D63+D64+D65+D66+D67+D68+D69+D70+D71 -> 223 | E72: =E46+E47+E48+E49+E50+E51+E52+E53+E54+E55+E56+E57+E58+E59+E60+E61+E62+E63+E64+E65+E66+E67+E68+E69+E70+E71 -> -67 | F72: =F46+F47+F48+F49+F50+F51+F52+F53+F54+F55+F56+F57+F58+F59+F60+F61+F62+F63+F64+F65+F66+F67+F68+F69+F70+F71 -> 1085 | G72: =G46+G47+G48+G49+G50+G51+G52+G53+G54+G55+G56+G57+G58+G59+G60+G61+G62+G63+G64+G65+G66+G67+G68+G69+G70+G71 -> 48 | H72: =H46+H47+H48+H49+H50+H51+H52+H53+H54+H55+H56+H57+H58+H59+H60+H61+H62+H63+H64+H65+H66+H67+H68+H69+H70+H71 -> 292 | I72: =I46+I47+I48+I49+I50+I51+I52+I53+I54+I55+I56+I57+I58+I59+I60+I61+I62+I63+I64+I65+I66+I67+I68+I69+I70+I71 -> -239 | ... K72: =K46+K47+K48+K49+K50+K51+K52+K53+K54+K55+K56+K57+K58+K59+K60+K61+K62+K63+K64+K65+K66+K67+K68+K69+K70+K71 -> -61
A74: RINGKASAN ARUS KAS
A75: Dampak Neto Perubahan Nilai Tukar | B75: -9 | C75: -7 | D75: 0 | E75: 0 | F75: 0 | G75: 0 | H75: 0 | I75: 0 | J75: 0 | K75: 0
A76: Kenaikan (Penurunan) Bersih Kas Dan Setara Kas | B76: =B18+B43+B72+B75 -> 845 | C76: =C18+C43+C72+C75 -> 152 | D76: =D18+D43+D72+D75 -> 73 | E76: =E18+E43+E72+E75 -> -108 | F76: =F18+F43+F72+F75 -> -1 | G76: =G18+G43+G72+G75 -> 240 | H76: =H18+H43+H72+H75 -> 23 | I76: =I18+I43+I72+I75 -> -165 | ... K76: =K18+K43+K72+K75 -> -122
A77: Kas Dan Setara Kas Awal Periode | B77: 742 | C77: 563 | D77: 465 | E77: 578 | F77: 554 | G77: 308 | H77: 279 | I77: 186 | J77: 176 | K77: 297
A78: Dampak Reklasifikasi Deposito | B78: 0 | C78: 0 | D78: 0 | E78: 0 | F78: 0 | G78: 0 | H78: 0 | I78: 0 | J78: 0 | K78: 0
A79: Dampak Perubahan Kepemilikan Entitas Anak | B79: 0 | C79: 0 | D79: 0 | E79: 0 | F79: 0 | G79: 0 | H79: 0 | I79: 0 | J79: 0 | K79: 0
A80: Penyesuaian Kas Setara Dan Setara Kas | B80: -67 | C80: 0 | D80: 0 | E80: 0 | F80: 0 | G80: 1 | H80: 0 | I80: 0 | J80: 0 | K80: 267
A81: Adjustment | B81: 0 | C81: 0 | D81: 0 | E81: 0 | F81: 0 | G81: 0 | H81: 0 | I81: 0 | J81: 0 | K81: 0
A82: Kas Dan Setara Kas Akhir Periode | B82: =B77+B76+B78+B79+B80+B81 -> 1520 | C82: =C77+C76+C78+C79+C80+C81 -> 715 | D82: =D77+D76+D78+D79+D80+D81 -> 538 | E82: =E77+E76+E78+E79+E80+E81 -> 470 | F82: =F77+F76+F78+F79+F80+F81 -> 553 | G82: =G77+G76+G78+G79+G80+G81 -> 549 | H82: =H77+H76+H78+H79+H80+H81 -> 302 | I82: =I77+I76+I78+I79+I80+I81 -> 21 | ... K82: =K77+K76+K78+K79+K80+K81 -> 442

Sheet DCF Valuation
A1: DCF VALUATION (FREE CASH FLOW TO EQUITY) - PT Rukun Raharja Tbk (RAJA)
A3: ASUMSI COST OF EQUITY (CAPM)
A4: Keterangan | B4: Nilai | C4: Satuan | H4: Sumber & Catatan
A5: Risk-Free Rate (Rf) | B5: 0.0734 | C5: %
A6: Equity Risk Premium (ERP) | B6: 0.06 | C6: %
A7: Beta (Adjusted, Blume Method) | B7: =0.67*'Market Data'!C13+0.33*1 -> 2.2462 | C7: x
A8: Cost of Equity (Ke) = Rf + Beta x ERP | B8: =B5+B7*B6 -> 0.208172 | C8: %
A10: Terminal Growth Rate (g) | B10: 0.03 | C10: %
A12: PROYEKSI FREE CASH FLOW TO EQUITY (FCFE) 2026F-2030F
A13: Keterangan | B13: 2026F | C13: 2027F | D13: 2028F | E13: 2029F | F13: 2030F
A14: FCFE (Miliar Rp) [= OCF - Capex, dari sheet Forecast] | B14: =Forecast!B44 -> 401.43154 | C14: =Forecast!C44 -> 532.26477 | D14: =Forecast!D44 -> 705.73873 | E14: =Forecast!E44 -> 935.75075 | F14: =Forecast!F44 -> 1240.7275
A15: Periode Diskonto (n, tahun) | B15: 1 | C15: 2 | D15: 3 | E15: 4 | F15: 5
A16: Faktor Diskonto = 1/(1+Ke)^n | B16: =1/(1+$B$8)^B15 -> 0.82769672 | C16: =1/(1+$B$8)^C15 -> 0.68508186 | D16: =1/(1+$B$8)^D15 -> 0.56704001 | E16: =1/(1+$B$8)^E15 -> 0.46933715 | F16: =1/(1+$B$8)^F15 -> 0.38846882
A17: PV of FCFE (Miliar Rp) | B17: =B14*B16 -> 332.26356 | C17: =C14*C16 -> 364.64494 | D17: =D14*D16 -> 400.18209 | E17: =E14*E16 -> 439.18259 | F17: =F14*F16 -> 481.98396
A19: TERMINAL VALUE (GORDON GROWTH)
A20: Keterangan | B20: Nilai | C20: Satuan
A21: FCFE Tahun 2030F (Miliar Rp) | B21: =F14 -> 1240.7275
A22: Terminal Value @ 2030 = FCFE2030x(1+g)/(Ke-g) | B22: =B21*(1+$B$10)/($B$8-$B$10) -> 7172.56
A23: PV of Terminal Value (Miliar Rp) | B23: =B22*F16 -> 2786.3159
A25: HASIL VALUASI DCF
A26: Total PV of FCFE 2026F-2030F (Miliar Rp) | B26: =SUM(B17:F17) -> 2018.2571
A27: PV of Terminal Value (Miliar Rp) | B27: =B23 -> 2786.3159
A28: Total Equity Value (Miliar Rp) | B28: =B26+B27 -> 4804.5731
A29: Jumlah Saham Beredar (Miliar Lembar) | B29: =Forecast!F18 -> 4.23
A30: DCF Value Per Share (Rp) | B30: =B28/B29 -> 1135.8329
A31: Harga Saham Saat Ini (Rp) | B31: ='Market Data'!C9 -> 890
A32: Upside / (Downside) vs Harga Saat Ini (%) | B32: =(B30-B31)/B31 -> 0.27621671

Sheet Relative Valuation
A1: RELATIVE VALUATION (PE, PBV, EV/EBITDA) - PT Rukun Raharja Tbk (RAJA)
A3: MULTIPLE RATA-RATA HISTORIS (12M 2016 - 12M 2025)
A4: Keterangan | B4: Rata-Rata 10 Thn | C4: Satuan | J4: Catatan
A5: PE Ratio (Rata-Rata 10 Tahun) | B5: =AVERAGE('Key Ratio'!B8:K8) -> 24.733785 | C5: x
A6: PBV Ratio (Rata-Rata 10 Tahun) | B6: =AVERAGE('Key Ratio'!B17:K17) -> 2.2652571 | C6: x
A7: EV/EBITDA (Rata-Rata, 2018-2025) | B7: =AVERAGE(B14:I14) -> 11.565896 | C7: x
A9: DATA PENDUKUNG EV/EBITDA HISTORIS (2018-2025, EBITDA tersedia sejak 2018)
A10: Keterangan | B10: 2018 | C10: 2019 | D10: 2020 | E10: 2021 | F10: 2022 | G10: 2023 | H10: 2024 | I10: 2025
A11: Enterprise Value (Miliar Rp) | B11: ='Market Data'!D30 -> 1763.75 | C11: ='Market Data'!E30 -> 1121.7 | D11: ='Market Data'!F30 -> 949.5 | E11: ='Market Data'!G30 -> 1743.4 | F11: ='Market Data'!H30 -> 5692.5 | G11: ='Market Data'!I30 -> 7524.3 | H11: ='Market Data'!J30 -> 12654.75 | I11: ='Market Data'!K30 -> 26831
A12: EBITDA (Miliar Rp) | B12: ='Key Ratio'!D10 -> 184.57 | C12: ='Key Ratio'!E10 -> 136.69 | D12: ='Key Ratio'!F10 -> 187.66 | E12: ='Key Ratio'!G10 -> 175.74 | F12: ='Key Ratio'!H10 -> 334.92 | G12: ='Key Ratio'!I10 -> 1000.02 | H12: ='Key Ratio'!J10 -> 1105.93 | I12: ='Key Ratio'!K10 -> 1126.33
A13: EBIT / Laba Usaha (Miliar Rp) | B13: ='Income Statement'!D9 -> 88 | C13: ='Income Statement'!E9 -> 40 | D13: ='Income Statement'!F9 -> 83 | E13: ='Income Statement'!G9 -> 66 | F13: ='Income Statement'!H9 -> 184 | G13: ='Income Statement'!I9 -> 733 | H13: ='Income Statement'!J9 -> 782 | I13: ='Income Statement'!K9 -> 772
A14: EV/EBITDA (x) | B14: =B11/B12 -> 9.555995 | C14: =C11/C12 -> 8.2061599 | D14: =D11/D12 -> 5.0596824 | E14: =E11/E12 -> 9.9203369 | F14: =F11/F12 -> 16.996596 | G14: =G11/G12 -> 7.5241495 | H14: =H11/H12 -> 11.442632 | I14: =I11/I12 -> 23.821615
A15: Rasio EBITDA / EBIT (x) | B15: =B12/B13 -> 2.0973864 | C15: =C12/C13 -> 3.41725 | D15: =D12/D13 -> 2.2609639 | E15: =E12/E13 -> 2.6627273 | F15: =F12/F13 -> 1.8202174 | G15: =G12/G13 -> 1.3642838 | H15: =H12/H13 -> 1.4142327 | I15: =I12/I13 -> 1.4589767
A17: PROYEKSI FY2026F UNTUK RELATIVE VALUATION
A18: Keterangan | B18: Nilai | C18: Satuan
A19: EPS 2026F (Rp) | B19: =Forecast!B31 -> 177.83838
A20: BVPS 2026F (Rp) | B20: =Forecast!B55 -> 965.27339
A21: EBIT 2026F (Miliar Rp) | B21: =Forecast!B24 -> 1074.6034
A22: EBITDA 2026F (Miliar Rp) = EBIT2026F x Rasio EBITDA/EBIT rata-rata | B22: =B21*AVERAGE(B15:I15) -> 2215.8373
A23: Net Debt 2026F (Miliar Rp) | B23: =Forecast!B47 -> 858.71838
A24: Jumlah Saham Beredar (Miliar Lembar) | B24: =Forecast!B18 -> 4.23
A26: IMPLIED VALUE PER SHARE
A27: Metode | B27: Implied Value (Rp/Saham) | C27: Catatan
A28: Metode PE (Rata-rata PE x EPS 2026F) | B28: =B5*B19 -> 4398.6163
A29: Metode PBV (Rata-rata PBV x BVPS 2026F) | B29: =B6*B20 -> 2186.5924
A30: Metode EV/EBITDA ((Rata-rata EV/EBITDA x EBITDA 2026F - Net Debt)/Saham) | B30: =(B7*B22-B23)/B24 -> 5855.6562
A31: Rata-Rata Relative Valuation | B31: =AVERAGE(B28:B30) -> 4146.955
A32: Harga Saham Saat Ini (Rp) | B32: ='Market Data'!C9 -> 890
A33: Upside / (Downside) vs Harga Saat Ini (%) | B33: =(B31-B32)/B32 -> 3.6595

Sheet Scenario Analysis
A1: SKENARIO BULL / BASE / BEAR - PT Rukun Raharja Tbk (RAJA)
A3: ASUMSI PER SKENARIO
A4: Keterangan | B4: Bear | C4: Base | D4: Bull
A5: Pertumbuhan Pendapatan (CAGR, %) | B5: =Forecast!B5-0.15 -> 0.061825659 | C5: =Forecast!B5 -> 0.21182566 | D5: =Forecast!B5+0.1 -> 0.31182566
A6: Margin Laba Kotor (%) | B6: =Forecast!B6-0.03 -> 0.25876101 | C6: =Forecast!B6 -> 0.28876101 | D6: =Forecast!B6+0.03 -> 0.31876101
A7: Beban Usaha (% Pendapatan, tetap di semua skenario) | B7: =Forecast!B7 -> 0.086948535 | C7: =Forecast!B7 -> 0.086948535 | D7: =Forecast!B7 -> 0.086948535
A8: Cost of Equity / Discount Rate (Ke, %) | B8: ='DCF Valuation'!B8+0.015 -> 0.223172 | C8: ='DCF Valuation'!B8 -> 0.208172 | D8: ='DCF Valuation'!B8-0.01 -> 0.198172
A9: Terminal Growth Rate (g, %) | B9: ='DCF Valuation'!B10-0.01 -> 0.02 | C9: ='DCF Valuation'!B10 -> 0.03 | D9: ='DCF Valuation'!B10+0.01 -> 0.04
A16: PROYEKSI 5 TAHUN - SKENARIO BEAR
A17: Keterangan | B17: 2026F | C17: 2027F | D17: 2028F | E17: 2029F | F17: 2030F
A18: Pendapatan (Miliar Rp) | B18: ='Income Statement'!K5*(1+$B$5) -> 4665.6619 | C18: =B18*(1+$B$5) -> 4954.1196 | D18: =C18*(1+$B$5) -> 5260.4113 | E18: =D18*(1+$B$5) -> 5585.6397 | F18: =E18*(1+$B$5) -> 5930.9755
A19: Laba Kotor (Miliar Rp) | B19: =B18*$B$6 -> 1207.2914 | C19: =C18*$B$6 -> 1281.933 | D19: =D18*$B$6 -> 1361.1894 | E19: =E18*$B$6 -> 1445.3458 | F19: =F18*$B$6 -> 1534.7052
A20: Beban Usaha (Miliar Rp) | B20: =-B18*$B$7 -> -405.67247 | C20: =-C18*$B$7 -> -430.75344 | D20: =-D18*$B$7 -> -457.38506 | E20: =-E18*$B$7 -> -485.66319 | F20: =-F18*$B$7 -> -515.68964
A21: EBIT / Laba Usaha (Miliar Rp) | B21: =B19+B20 -> 801.61894 | C21: =C19+C20 -> 851.17956 | D21: =D19+D20 -> 903.8043 | E21: =E19+E20 -> 959.6826 | F21: =F19+F20 -> 1019.0156
A22: FCFE (Miliar Rp) = EBIT x Rasio FCFE/EBIT Forecast | B22: =B21*(Forecast!B44/Forecast!B24) -> 299.45478 | C22: =C21*(Forecast!C44/Forecast!C24) -> 317.96877 | D22: =D21*(Forecast!D44/Forecast!D24) -> 337.62739 | E22: =E21*(Forecast!E44/Forecast!E24) -> 358.50143 | F22: =F21*(Forecast!F44/Forecast!F24) -> 380.66602
A23: Faktor Diskonto = 1/(1+Ke)^n | B23: =1/(1+$B$8)^1 -> 0.81754651 | C23: =1/(1+$B$8)^2 -> 0.6683823 | D23: =1/(1+$B$8)^3 -> 0.54643361 | E23: =1/(1+$B$8)^4 -> 0.44673489 | F23: =1/(1+$B$8)^5 -> 0.36522655
A24: PV of FCFE (Miliar Rp) | B24: =B22*B23 -> 244.81821 | C24: =C22*C23 -> 212.52469 | D24: =D22*D23 -> 184.49096 | E24: =E22*E23 -> 160.1551 | F24: =F22*F23 -> 139.02934
A25: Terminal Value @2030 & PV-nya (Miliar Rp) | B25: =F22*(1+$B$9)/($B$8-$B$9)*F23 -> 697.97967
A26: Total Equity Value (Miliar Rp) | B26: =SUM(B24:F24)+B25 -> 1638.998
A27: Target Harga Skenario Bear (Rp/Saham) | B27: =B26/Forecast!F18 -> 387.46997
A29: PROYEKSI 5 TAHUN - SKENARIO BASE
A30: Keterangan | B30: 2026F | C30: 2027F | D30: 2028F | E30: 2029F | F30: 2030F
A31: Pendapatan (Miliar Rp) | B31: ='Income Statement'!K5*(1+$C$5) -> 5324.7619 | C31: =B31*(1+$C$5) -> 6452.6832 | D31: =C31*(1+$C$5) -> 7819.527 | E31: =D31*(1+$C$5) -> 9475.9035 | F31: =E31*(1+$C$5) -> 11483.143
A32: Laba Kotor (Miliar Rp) | B32: =B31*$C$6 -> 1537.5837 | C32: =C31*$C$6 -> 1863.2833 | D32: =D31*$C$6 -> 2257.9746 | E32: =E31*$C$6 -> 2736.2715 | F32: =F31*$C$6 -> 3315.884
A33: Beban Usaha (Miliar Rp) | B33: =-B31*$C$7 -> -462.98025 | C33: =-C31*$C$7 -> -561.05135 | D33: =-D31*$C$7 -> -679.89642 | E33: =-E31*$C$7 -> -823.91593 | F33: =-F31*$C$7 -> -998.44246
A34: EBIT / Laba Usaha (Miliar Rp) | B34: =B32+B33 -> 1074.6034 | C34: =C32+C33 -> 1302.232 | D34: =D32+D33 -> 1578.0781 | E34: =E32+E33 -> 1912.3556 | F34: =F32+F33 -> 2317.4416
A35: FCFE (Miliar Rp) = EBIT x Rasio FCFE/EBIT Forecast | B35: =B34*(Forecast!B44/Forecast!B24) -> 401.43154 | C35: =C34*(Forecast!C44/Forecast!C24) -> 486.46504 | D35: =D34*(Forecast!D44/Forecast!D24) -> 589.51081 | E35: =E34*(Forecast!E44/Forecast!E24) -> 714.38433 | F35: =F34*(Forecast!F44/Forecast!F24) -> 865.70926
A36: Faktor Diskonto = 1/(1+Ke)^n | B36: =1/(1+$C$8)^1 -> 0.82769672 | C36: =1/(1+$C$8)^2 -> 0.68508186 | D36: =1/(1+$C$8)^3 -> 0.56704001 | E36: =1/(1+$C$8)^4 -> 0.46933715 | F36: =1/(1+$C$8)^5 -> 0.38846882
A37: PV of FCFE (Miliar Rp) | B37: =B35*B36 -> 332.26356 | C37: =C35*C36 -> 333.26837 | D37: =D35*D36 -> 334.27621 | E37: =E35*E36 -> 335.28711 | F37: =F35*F36 -> 336.30106
A38: Terminal Value @2030 & PV-nya (Miliar Rp) | B38: =F35*(1+$C$9)/($C$8-$C$9)*F36 -> 1944.1331
A39: Total Equity Value (Miliar Rp) | B39: =SUM(B37:F37)+B38 -> 3615.5294
A40: Target Harga Skenario Base (Rp/Saham) | B40: =B39/Forecast!F18 -> 854.73509
A42: PROYEKSI 5 TAHUN - SKENARIO BULL
A43: Keterangan | B43: 2026F | C43: 2027F | D43: 2028F | E43: 2029F | F43: 2030F
A44: Pendapatan (Miliar Rp) | B44: ='Income Statement'!K5*(1+$D$5) -> 5764.1619 | C44: =B44*(1+$D$5) -> 7561.5755 | D44: =C44*(1+$D$5) -> 9919.4688 | E44: =D44*(1+$D$5) -> 13012.614 | F44: =E44*(1+$D$5) -> 17070.281
A45: Laba Kotor (Miliar Rp) | B45: =B44*$D$6 -> 1837.3901 | C45: =C44*$D$6 -> 2410.3355 | D45: =D44*$D$6 -> 3161.9399 | E45: =E44*$D$6 -> 4147.9139 | F45: =F44*$D$6 -> 5441.34
A46: Beban Usaha (Miliar Rp) | B46: =-B44*$D$7 -> -501.18544 | C46: =-C44*$D$7 -> -657.46792 | D46: =-D44*$D$7 -> -862.48328 | E46: =-E44*$D$7 -> -1131.4277 | F46: =-F44*$D$7 -> -1484.2359
A47: EBIT / Laba Usaha (Miliar Rp) | B47: =B45+B46 -> 1336.2047 | C47: =C45+C46 -> 1752.8676 | D47: =D45+D46 -> 2299.4567 | E47: =E45+E46 -> 3016.4862 | F47: =F45+F46 -> 3957.1041
A48: FCFE (Miliar Rp) = EBIT x Rasio FCFE/EBIT Forecast | B48: =B47*(Forecast!B44/Forecast!B24) -> 499.15596 | C48: =C47*(Forecast!C44/Forecast!C24) -> 654.80559 | D48: =D47*(Forecast!D44/Forecast!D24) -> 858.99078 | E48: =E47*(Forecast!E44/Forecast!E24) -> 1126.8461 | F48: =F47*(Forecast!F44/Forecast!F24) -> 1478.2257
A49: Faktor Diskonto = 1/(1+Ke)^n | B49: =1/(1+$D$8)^1 -> 0.83460471 | C49: =1/(1+$D$8)^2 -> 0.69656503 | D49: =1/(1+$D$8)^3 -> 0.58135646 | E49: =1/(1+$D$8)^4 -> 0.48520284 | F49: =1/(1+$D$8)^5 -> 0.40495258
A50: PV of FCFE (Miliar Rp) | B50: =B48*B49 -> 416.59791 | C50: =C48*C49 -> 456.11468 | D50: =D48*D49 -> 499.37984 | E50: =E48*E49 -> 546.74895 | F50: =F48*F49 -> 598.6113
A51: Terminal Value @2030 & PV-nya (Miliar Rp) | B51: =F48*(1+$D$9)/($D$8-$D$9)*F49 -> 3935.9416
A52: Total Equity Value (Miliar Rp) | B52: =SUM(B50:F50)+B51 -> 6453.3943
A53: Target Harga Skenario Bull (Rp/Saham) | B53: =B52/Forecast!F18 -> 1525.6251
A56: RINGKASAN TARGET HARGA PER SKENARIO
A57: Skenario | B57: Target Harga (Rp) | C57: Upside/(Downside) vs Harga Saat Ini
A58: Bear | B58: =B27 -> 387.46997 | C58: =(B58-'Market Data'!C9)/'Market Data'!C9 -> -0.56464049
A59: Base | B59: =B40 -> 854.73509 | C59: =(B59-'Market Data'!C9)/'Market Data'!C9 -> -0.039623493
A60: Bull | B60: =B53 -> 1525.6251 | C60: =(B60-'Market Data'!C9)/'Market Data'!C9 -> 0.71418553

Sheet Sensitivity Analysis
A1: SENSITIVITY ANALYSIS - DCF VALUE PER SHARE - PT Rukun Raharja Tbk (RAJA)
A3: SENSITIVITAS: COST OF EQUITY (Ke) vs TERMINAL GROWTH (g)
A4: Nilai wajar per saham (Rp) hasil DCF-FCFE untuk kombinasi Ke dan g. Baris = Ke, Kolom = g. Sel yang disorot kuning adalah kombinasi Base Case (harus sama dengan sheet DCF Valuation).
A7: Ke \ g | C7: ='DCF Valuation'!$B$10-0.01 -> 0.02 | D7: ='DCF Valuation'!$B$10-0.005 -> 0.025 | E7: ='DCF Valuation'!$B$10 -> 0.03 | F7: ='DCF Valuation'!$B$10+0.005 -> 0.035 | G7: ='DCF Valuation'!$B$10+0.01 -> 0.04
B8: ='DCF Valuation'!$B$8-0.02 -> 0.188172 | C8: =(Forecast!$B$44/(1+$B8)^1+Forecast!$C$44/(1+$B8)^2+Forecast!$D$44/(1+$B8)^3+Forecast!$E$44/(1+$B8)^4+Forecast!$F$44/(1+$B8)^5+(Forecast!$F$44*(1+C$7)/($B8-C$7))/(1+$B8)^5)/'DCF Valuation'!$B$29 -> 1254.5762 | D8: =(Forecast!$B$44/(1+$B8)^1+Forecast!$C$44/(1+$B8)^2+Forecast!$D$44/(1+$B8)^3+Forecast!$E$44/(1+$B8)^4+Forecast!$F$44/(1+$B8)^5+(Forecast!$F$44*(1+D$7)/($B8-D$7))/(1+$B8)^5)/'DCF Valuation'!$B$29 -> 1281.3919 | E8: =(Forecast!$B$44/(1+$B8)^1+Forecast!$C$44/(1+$B8)^2+Forecast!$D$44/(1+$B8)^3+Forecast!$E$44/(1+$B8)^4+Forecast!$F$44/(1+$B8)^5+(Forecast!$F$44*(1+E$7)/($B8-E$7))/(1+$B8)^5)/'DCF Valuation'!$B$29 -> 1309.9029 | F8: =(Forecast!$B$44/(1+$B8)^1+Forecast!$C$44/(1+$B8)^2+Forecast!$D$44/(1+$B8)^3+Forecast!$E$44/(1+$B8)^4+Forecast!$F$44/(1+$B8)^5+(Forecast!$F$44*(1+F$7)/($B8-F$7))/(1+$B8)^5)/'DCF Valuation'!$B$29 -> 1340.2754 | G8: =(Forecast!$B$44/(1+$B8)^1+Forecast!$C$44/(1+$B8)^2+Forecast!$D$44/(1+$B8)^3+Forecast!$E$44/(1+$B8)^4+Forecast!$F$44/(1+$B8)^5+(Forecast!$F$44*(1+G$7)/($B8-G$7))/(1+$B8)^5)/'DCF Valuation'!$B$29 -> 1372.6977
B9: ='DCF Valuation'!$B$8-0.01 -> 0.198172 | C9: =(Forecast!$B$44/(1+$B9)^1+Forecast!$C$44/(1+$B9)^2+Forecast!$D$44/(1+$B9)^3+Forecast!$E$44/(1+$B9)^4+Forecast!$F$44/(1+$B9)^5+(Forecast!$F$44*(1+C$7)/($B9-C$7))/(1+$B9)^5)/'DCF Valuation'!$B$29 -> 1169.9507 | D9: =(Forecast!$B$44/(1+$B9)^1+Forecast!$C$44/(1+$B9)^2+Forecast!$D$44/(1+$B9)^3+Forecast!$E$44/(1+$B9)^4+Forecast!$F$44/(1+$B9)^5+(Forecast!$F$44*(1+D$7)/($B9-D$7))/(1+$B9)^5)/'DCF Valuation'!$B$29 -> 1193.0135 | E9: =(Forecast!$B$44/(1+$B9)^1+Forecast!$C$44/(1+$B9)^2+Forecast!$D$44/(1+$B9)^3+Forecast!$E$44/(1+$B9)^4+Forecast!$F$44/(1+$B9)^5+(Forecast!$F$44*(1+E$7)/($B9-E$7))/(1+$B9)^5)/'DCF Valuation'!$B$29 -> 1217.4477 | F9: =(Forecast!$B$44/(1+$B9)^1+Forecast!$C$44/(1+$B9)^2+Forecast!$D$44/(1+$B9)^3+Forecast!$E$44/(1+$B9)^4+Forecast!$F$44/(1+$B9)^5+(Forecast!$F$44*(1+F$7)/($B9-F$7))/(1+$B9)^5)/'DCF Valuation'!$B$29 -> 1243.3793 | G9: =(Forecast!$B$44/(1+$B9)^1+Forecast!$C$44/(1+$B9)^2+Forecast!$D$44/(1+$B9)^3+Forecast!$E$44/(1+$B9)^4+Forecast!$F$44/(1+$B9)^5+(Forecast!$F$44*(1+G$7)/($B9-G$7))/(1+$B9)^5)/'DCF Valuation'!$B$29 -> 1270.9504
B10: ='DCF Valuation'!$B$8 -> 0.208172 | C10: =(Forecast!$B$44/(1+$B10)^1+Forecast!$C$44/(1+$B10)^2+Forecast!$D$44/(1+$B10)^3+Forecast!$E$44/(1+$B10)^4+Forecast!$F$44/(1+$B10)^5+(Forecast!$F$44*(1+C$7)/($B10-C$7))/(1+$B10)^5)/'DCF Valuation'!$B$29 -> 1094.7722 | D10: =(Forecast!$B$44/(1+$B10)^1+Forecast!$C$44/(1+$B10)^2+Forecast!$D$44/(1+$B10)^3+Forecast!$E$44/(1+$B10)^4+Forecast!$F$44/(1+$B10)^5+(Forecast!$F$44*(1+D$7)/($B10-D$7))/(1+$B10)^5)/'DCF Valuation'!$B$29 -> 1114.7421 | E10: =(Forecast!$B$44/(1+$B10)^1+Forecast!$C$44/(1+$B10)^2+Forecast!$D$44/(1+$B10)^3+Forecast!$E$44/(1+$B10)^4+Forecast!$F$44/(1+$B10)^5+(Forecast!$F$44*(1+E$7)/($B10-E$7))/(1+$B10)^5)/'DCF Valuation'!$B$29 -> 1135.8329 | F10: =(Forecast!$B$44/(1+$B10)^1+Forecast!$C$44/(1+$B10)^2+Forecast!$D$44/(1+$B10)^3+Forecast!$E$44/(1+$B10)^4+Forecast!$F$44/(1+$B10)^5+(Forecast!$F$44*(1+F$7)/($B10-F$7))/(1+$B10)^5)/'DCF Valuation'!$B$29 -> 1158.1416 | G10: =(Forecast!$B$44/(1+$B10)^1+Forecast!$C$44/(1+$B10)^2+Forecast!$D$44/(1+$B10)^3+Forecast!$E$44/(1+$B10)^4+Forecast!$F$44/(1+$B10)^5+(Forecast!$F$44*(1+G$7)/($B10-G$7))/(1+$B10)^5)/'DCF Valuation'!$B$29 -> 1181.7768
B11: ='DCF Valuation'!$B$8+0.01 -> 0.218172 | C11: =(Forecast!$B$44/(1+$B11)^1+Forecast!$C$44/(1+$B11)^2+Forecast!$D$44/(1+$B11)^3+Forecast!$E$44/(1+$B11)^4+Forecast!$F$44/(1+$B11)^5+(Forecast!$F$44*(1+C$7)/($B11-C$7))/(1+$B11)^5)/'DCF Valuation'!$B$29 -> 1027.5919 | D11: =(Forecast!$B$44/(1+$B11)^1+Forecast!$C$44/(1+$B11)^2+Forecast!$D$44/(1+$B11)^3+Forecast!$E$44/(1+$B11)^4+Forecast!$F$44/(1+$B11)^5+(Forecast!$F$44*(1+D$7)/($B11-D$7))/(1+$B11)^5)/'DCF Valuation'!$B$29 -> 1044.9893 | E11: =(Forecast!$B$44/(1+$B11)^1+Forecast!$C$44/(1+$B11)^2+Forecast!$D$44/(1+$B11)^3+Forecast!$E$44/(1+$B11)^4+Forecast!$F$44/(1+$B11)^5+(Forecast!$F$44*(1+E$7)/($B11-E$7))/(1+$B11)^5)/'DCF Valuation'!$B$29 -> 1063.3113 | F11: =(Forecast!$B$44/(1+$B11)^1+Forecast!$C$44/(1+$B11)^2+Forecast!$D$44/(1+$B11)^3+Forecast!$E$44/(1+$B11)^4+Forecast!$F$44/(1+$B11)^5+(Forecast!$F$44*(1+F$7)/($B11-F$7))/(1+$B11)^5)/'DCF Valuation'!$B$29 -> 1082.6336 | G11: =(Forecast!$B$44/(1+$B11)^1+Forecast!$C$44/(1+$B11)^2+Forecast!$D$44/(1+$B11)^3+Forecast!$E$44/(1+$B11)^4+Forecast!$F$44/(1+$B11)^5+(Forecast!$F$44*(1+G$7)/($B11-G$7))/(1+$B11)^5)/'DCF Valuation'!$B$29 -> 1103.0403
B12: ='DCF Valuation'!$B$8+0.02 -> 0.228172 | C12: =(Forecast!$B$44/(1+$B12)^1+Forecast!$C$44/(1+$B12)^2+Forecast!$D$44/(1+$B12)^3+Forecast!$E$44/(1+$B12)^4+Forecast!$F$44/(1+$B12)^5+(Forecast!$F$44*(1+C$7)/($B12-C$7))/(1+$B12)^5)/'DCF Valuation'!$B$29 -> 967.24047 | D12: =(Forecast!$B$44/(1+$B12)^1+Forecast!$C$44/(1+$B12)^2+Forecast!$D$44/(1+$B12)^3+Forecast!$E$44/(1+$B12)^4+Forecast!$F$44/(1+$B12)^5+(Forecast!$F$44*(1+D$7)/($B12-D$7))/(1+$B12)^5)/'DCF Valuation'!$B$29 -> 982.48041 | E12: =(Forecast!$B$44/(1+$B12)^1+Forecast!$C$44/(1+$B12)^2+Forecast!$D$44/(1+$B12)^3+Forecast!$E$44/(1+$B12)^4+Forecast!$F$44/(1+$B12)^5+(Forecast!$F$44*(1+E$7)/($B12-E$7))/(1+$B12)^5)/'DCF Valuation'!$B$29 -> 998.48937 | F12: =(Forecast!$B$44/(1+$B12)^1+Forecast!$C$44/(1+$B12)^2+Forecast!$D$44/(1+$B12)^3+Forecast!$E$44/(1+$B12)^4+Forecast!$F$44/(1+$B12)^5+(Forecast!$F$44*(1+F$7)/($B12-F$7))/(1+$B12)^5)/'DCF Valuation'!$B$29 -> 1015.3271 | G12: =(Forecast!$B$44/(1+$B12)^1+Forecast!$C$44/(1+$B12)^2+Forecast!$D$44/(1+$B12)^3+Forecast!$E$44/(1+$B12)^4+Forecast!$F$44/(1+$B12)^5+(Forecast!$F$44*(1+G$7)/($B12-G$7))/(1+$B12)^5)/'DCF Valuation'!$B$29 -> 1033.0596
A15: Cek: sel yang disorot kuning (Ke Base, g Base) harus identik dengan "DCF Value Per Share" pada sheet DCF Valuation.
A18: Cross-check: DCF Value Per Share (dari sheet DCF Valuation) | B18: ='DCF Valuation'!B30 -> 1135.8329

Sheet Valuation Summary
A1: VALUATION SUMMARY & INVESTMENT RATING - PT Rukun Raharja Tbk (RAJA)
A3: RINGKASAN VALUASI (TARGET HARGA OTOMATIS)
A4: Metode | B4: Nilai (Rp/Saham) | C4: Bobot (%) | F4: Catatan
A5: DCF Valuation (FCFE) | B5: ='DCF Valuation'!B30 -> 1135.8329 | C5: 0.6
A6: Relative Valuation (Rata-rata PE/PBV/EV-EBITDA) | B6: ='Relative Valuation'!B31 -> 4146.955 | C6: 0.4
A7: TARGET HARGA (Weighted Average) | B7: =SUMPRODUCT(B5:B6,C5:C6)/SUM(C5:C6) -> 2340.2817
A9: Harga Saham Saat Ini (Rp) | B9: ='Market Data'!C9 -> 890
A10: Upside / (Downside) terhadap Target (%) | B10: =(B7-B9)/B9 -> 1.62953
A12: TARGET HARGA SKENARIO BULL / BASE / BEAR
A13: Skenario | B13: Target Harga (Rp) | C13: Upside/(Downside)
A14: Bear | B14: ='Scenario Analysis'!B27 -> 387.46997 | C14: =(B14-B9)/B9 -> -0.56464049
A15: Base | B15: ='Scenario Analysis'!B40 -> 854.73509 | C15: =(B15-B9)/B9 -> -0.039623493
A16: Bull | B16: ='Scenario Analysis'!B53 -> 1525.6251 | C16: =(B16-B9)/B9 -> 0.71418553
A18: RATING INVESTASI OTOMATIS
A19: Keterangan | B19: Nilai | C19: Satuan | F19: Catatan
A20: Threshold BUY (Upside minimal) | B20: 0.15
A21: Threshold SELL (Downside maksimal) | B21: -0.1
A22: RATING INVESTASI | B22: =IF(B10>=B20,"BUY",IF(B10<=B21,"SELL","HOLD")) -> BUY

Sheet Dashboard
A1: DASHBOARD - PT Rukun Raharja Tbk (RAJA)
A3: RINGKASAN INVESTASI
B4: Harga Saat Ini (Rp) | C4: Target Harga (Rp) | D4: Upside/(Downside) | E4: Rating Investasi | F4: Target Bear (Rp) | G4: Target Base (Rp) | H4: Target Bull (Rp)
B5: ='Valuation Summary'!B9 -> 890 | C5: ='Valuation Summary'!B7 -> 2340.2817 | D5: ='Valuation Summary'!B10 -> 1.62953 | E5: ='Valuation Summary'!B22 -> BUY | F5: ='Valuation Summary'!B14 -> 387.46997 | G5: ='Valuation Summary'!B15 -> 854.73509 | H5: ='Valuation Summary'!B16 -> 1525.6251
A8: DATA PENDUKUNG GRAFIK (JANGAN DIHAPUS)
A9: Keterangan | B9: 12M 2016 | C9: 12M 2017 | D9: 12M 2018 | E9: 12M 2019 | F9: 12M 2020 | G9: 12M 2021 | H9: 12M 2022 | I9: 12M 2023 | J9: 12M 2024 | K9: 12M 2025
A10: Net Margin (%) = Laba Bersih Pemilik / Pendapatan | B10: ='Income Statement'!B30/'Income Statement'!B5 -> 0.034981906 | C10: ='Income Statement'!C30/'Income Statement'!C5 -> 0.078273959 | D10: ='Income Statement'!D30/'Income Statement'!D5 -> 0.096850862 | E10: ='Income Statement'!E30/'Income Statement'!E5 -> 0.046875 | F10: ='Income Statement'!F30/'Income Statement'!F5 -> 0.013888889 | G10: ='Income Statement'!G30/'Income Statement'!G5 -> 0.022775801 | H10: ='Income Statement'!H30/'Income Statement'!H5 -> 0.069496021 | I10: ='Income Statement'!I30/'Income Statement'!I5 -> 0.12580438 | ... K10: ='Income Statement'!K30/'Income Statement'!K5 -> 0.1021848
